{"format":"compact-registry-v2-seed-batch-v1","verified_at":"2026-04-26","defaults":{"scope":"merchant","acceptance_type":"direct_crypto","supports_program_or_network":"BTC Map / OpenStreetMap","confidence":"low","evidence_kind":"official_store_locator","evidence_publisher":"BTC Map / OpenStreetMap contributors","source_origin":"community_seed","support_rails":[{"rail_id":"asset:bitcoin","rail_type":"asset","label":"Bitcoin"},{"rail_id":"chain:lightning","rail_type":"chain","label":"Lightning Network"}],"notes":["BTC Map is powered by OpenStreetMap/community-maintained location data.","Physical/local merchant seed; verify merchant-side evidence before raising confidence."]},"sources":{"btcmap-v4-places":{"label":"BTC Map REST API v4 places","url":"https://api.btcmap.org/v4/places?fields=id%2Cname%2Clat%2Clon%2Caddress%2Cwebsite%2Cupdated_at%2Cverified_at%2Cosm_id%2Cosm_url%2Cpayment_provider&updated_since=1970-01-01T00%3A00%3A00Z&limit=250","publisher":"BTC Map / OpenStreetMap contributors","kind":"official_store_locator"}},"entries":[{"id":"merchant:print-2-media-ltd:btcmap-place-9906","name":"Print 2 Media Ltd.","source":"btcmap-v4-places","website":"https://www.print-2-media.com/","country":null,"city":null,"explicit_support":"Print 2 Media Ltd. is listed in BTC Map as a physical place that accepts Bitcoin.","notes":["BTC Map place id: 9906","BTC Map verified_at: 2022-10-17","BTC Map updated_at: 2025-09-18T05:36:30.609Z","BTC Map address: Unit 7 Moorswater Industrial Estate Liskeard PL14 4LN","OSM: https://www.openstreetmap.org/node/3011053668","lat/lon: 50.4523118, -4.4872693"]},{"id":"merchant:nordre-pjaaka-gard:btcmap-place-10209","name":"NORDRE PJAAKA GÅRD","source":"btcmap-v4-places","website":"https://www.facebook.com/alvegg.no","country":null,"city":null,"explicit_support":"NORDRE PJAAKA GÅRD is listed in BTC Map as a physical place that accepts Bitcoin.","notes":["BTC Map place id: 10209","BTC Map verified_at: 2022-10-11","BTC Map updated_at: 2025-09-18T05:36:30.609Z","OSM: https://www.openstreetmap.org/node/3130117910","lat/lon: 60.125197, 10.368725"]},{"id":"merchant:native-ceuticals:btcmap-place-11440","name":"Native Ceuticals","source":"btcmap-v4-places","website":"https://nativeceuticals.com/","country":null,"city":null,"explicit_support":"Native Ceuticals is listed in BTC Map as a physical place that accepts Bitcoin.","notes":["BTC Map place id: 11440","BTC Map verified_at: 2022-10-04","BTC Map updated_at: 2025-09-18T05:36:30.61Z","BTC Map address: 331 Alcove Road Mooresville 28117","OSM: https://www.openstreetmap.org/node/4059261402","lat/lon: 35.5425865, -80.8604508"]},{"id":"merchant:mountain-stream-tea:btcmap-place-11474","name":"檳榔攤 (Mountain Stream Tea)","source":"btcmap-v4-places","website":null,"country":null,"city":null,"explicit_support":"檳榔攤 (Mountain Stream Tea) is listed in BTC Map as a physical place that accepts Bitcoin.","notes":["BTC Map place id: 11474","BTC Map verified_at: 2022-10-19","BTC Map updated_at: 2025-09-18T05:36:30.61Z","OSM: https://www.openstreetmap.org/node/4135000754","lat/lon: 23.9885313, 121.6061806"]},{"id":"merchant:bambu-guest-house:btcmap-place-12318","name":"Bambu Guest House","source":"btcmap-v4-places","website":"https://www.bambuguesthouse.com/","country":null,"city":null,"explicit_support":"Bambu Guest House is listed in BTC Map as a physical place that accepts Bitcoin.","notes":["BTC Map place id: 12318","BTC Map verified_at: 2022-10-02","BTC Map updated_at: 2025-09-18T05:36:30.61Z","OSM: https://www.openstreetmap.org/node/5288343322","lat/lon: 14.7350789, -91.2481426"]},{"id":"merchant:bounce-creative-designs:btcmap-place-12795","name":"Bounce Creative Designs","source":"btcmap-v4-places","website":null,"country":null,"city":null,"explicit_support":"Bounce Creative Designs is listed in BTC Map as a physical place that accepts Bitcoin.","notes":["BTC Map place id: 12795","BTC Map verified_at: 2022-09-26","BTC Map updated_at: 2025-09-18T05:36:30.61Z","OSM: https://www.openstreetmap.org/node/5842194434","lat/lon: 51.4814099, -0.0573876"]},{"id":"merchant:ar-photography:btcmap-place-13571","name":"AR Photography","source":"btcmap-v4-places","website":"https://www.ar.photography/","country":null,"city":null,"explicit_support":"AR Photography is listed in BTC Map as a physical place that accepts Bitcoin.","notes":["BTC Map place id: 13571","BTC Map verified_at: 2022-10-19","BTC Map updated_at: 2025-09-18T05:36:30.611Z","BTC Map address: 162 Park Street Montclair 07042","OSM: https://www.openstreetmap.org/node/7320800293","lat/lon: 40.8247951, -74.2105702"]},{"id":"merchant:iq-jersey-apple-premium-reseller:btcmap-place-14131","name":"iQ Jersey Apple Premium Reseller","source":"btcmap-v4-places","website":"http://www.iqjersey.com/","country":null,"city":null,"explicit_support":"iQ Jersey Apple Premium Reseller is listed in BTC Map as a physical place that accepts Bitcoin.","notes":["BTC Map place id: 14131","BTC Map verified_at: 2022-10-04","BTC Map updated_at: 2025-09-18T05:36:30.611Z","OSM: https://www.openstreetmap.org/node/9008694889","lat/lon: 49.1833875, -2.1108811"]},{"id":"merchant:bayramoglu-ayakkab:btcmap-place-14624","name":"Bayramoğlu Ayakkabı","source":"btcmap-v4-places","website":null,"country":null,"city":null,"explicit_support":"Bayramoğlu Ayakkabı is listed in BTC Map as a physical place that accepts Bitcoin.","notes":["BTC Map place id: 14624","BTC Map verified_at: 2022-10-22","BTC Map updated_at: 2025-09-18T05:36:30.612Z","OSM: https://www.openstreetmap.org/node/9958759626","lat/lon: 35.1828074, 33.351843"]},{"id":"merchant:dandy-farmer:btcmap-place-14626","name":"Dandy Farmer","source":"btcmap-v4-places","website":"https://www.dandyfarmer.com","country":null,"city":null,"explicit_support":"Dandy Farmer is listed in BTC Map as a physical place that accepts Bitcoin.","notes":["BTC Map place id: 14626","BTC Map verified_at: 2022-10-19","BTC Map updated_at: 2025-09-18T05:36:30.612Z","BTC Map address: 14 Clermont Avenue Brooklyn 11205","OSM: https://www.openstreetmap.org/node/9964721813","lat/lon: 40.697432, -73.9718971"]},{"id":"merchant:bbq-stand-nightly:btcmap-place-153","name":"BBQ Stand Nightly","source":"btcmap-v4-places","website":null,"country":null,"city":null,"explicit_support":"BBQ Stand Nightly is listed in BTC Map as a physical place that accepts Bitcoin.","notes":["BTC Map place id: 153","BTC Map verified_at: 2022-09-27","BTC Map updated_at: 2025-09-18T05:36:30.613Z","OSM: https://www.openstreetmap.org/node/10055169478","lat/lon: 11.9536454, 121.9378672"]},{"id":"merchant:silver-bullion-pte-ltd:btcmap-place-1068","name":"Silver Bullion Pte Ltd","source":"btcmap-v4-places","website":"https://www.silverbullion.com.sg/","country":null,"city":null,"explicit_support":"Silver Bullion Pte Ltd is listed in BTC Map as a physical place that accepts Bitcoin.","notes":["BTC Map place id: 1068","BTC Map verified_at: 2022-11-06","BTC Map updated_at: 2025-09-18T05:36:30.613Z","BTC Map address: Raffles Boulevard Singapore 039596","OSM: https://www.openstreetmap.org/node/10162798341","lat/lon: 1.2922924, 103.8598055"]},{"id":"merchant:gide-get-hb:btcmap-place-6500","name":"Gide Get HB","source":"btcmap-v4-places","website":"http://gideget.se","country":null,"city":null,"explicit_support":"Gide Get HB is listed in BTC Map as a physical place that accepts Bitcoin.","notes":["BTC Map place id: 6500","BTC Map verified_at: 2022-11-04","BTC Map updated_at: 2025-09-18T05:36:30.613Z","BTC Map address: 125 Djuptjärn TREHÖRNINGSJÖ 89054","OSM: https://www.openstreetmap.org/node/2467059186","lat/lon: 63.7188423, 18.7040275"]},{"id":"merchant:mcchip-dkr:btcmap-place-8349","name":"mcchip-dkr","source":"btcmap-v4-places","website":"https://mcchip-dkr.com/","country":null,"city":null,"explicit_support":"mcchip-dkr is listed in BTC Map as a physical place that accepts Bitcoin.","notes":["BTC Map place id: 8349","BTC Map verified_at: 2022-11-04","BTC Map updated_at: 2025-09-18T05:36:30.614Z","BTC Map address: 16 Christian-Schlömer-Ring Mechernich 53894","OSM: https://www.openstreetmap.org/node/2703454280","lat/lon: 50.6406163, 6.7038843"]},{"id":"merchant:servis-znojmo:btcmap-place-8979","name":"Servis Znojmo","source":"btcmap-v4-places","website":null,"country":null,"city":null,"explicit_support":"Servis Znojmo is listed in BTC Map as a physical place that accepts Bitcoin.","notes":["BTC Map place id: 8979","BTC Map verified_at: 2022-11-04","BTC Map updated_at: 2025-09-18T05:36:30.614Z","BTC Map address: 2637/36 Loucká 67181","OSM: https://www.openstreetmap.org/node/2778587874","lat/lon: 48.8397049, 16.0564184"]},{"id":"merchant:carenderia-pjds:btcmap-place-155","name":"Carenderia PJDS","source":"btcmap-v4-places","website":null,"country":null,"city":null,"explicit_support":"Carenderia PJDS is listed in BTC Map as a physical place that accepts Bitcoin.","notes":["BTC Map place id: 155","BTC Map verified_at: 2022-09-27","BTC Map updated_at: 2025-09-18T05:36:30.615Z","OSM: https://www.openstreetmap.org/node/10055171968","lat/lon: 11.9565226, 121.9319822"]},{"id":"merchant:witchy-bitchy-beauty-spot-and-original-import:btcmap-place-13358","name":"Witchy Bitchy Beauty Spot & Original Import","source":"btcmap-v4-places","website":null,"country":null,"city":null,"explicit_support":"Witchy Bitchy Beauty Spot & Original Import is listed in BTC Map as a physical place that accepts Bitcoin.","notes":["BTC Map place id: 13358","BTC Map verified_at: 2022-11-04","BTC Map updated_at: 2025-09-18T05:36:30.615Z","OSM: https://www.openstreetmap.org/node/6802499425","lat/lon: 60.397987, 5.326432"]},{"id":"merchant:carenderia-devine-refreshment:btcmap-place-157","name":"Carenderia Devine Refreshment","source":"btcmap-v4-places","website":null,"country":null,"city":null,"explicit_support":"Carenderia Devine Refreshment is listed in BTC Map as a physical place that accepts Bitcoin.","notes":["BTC Map place id: 157","BTC Map verified_at: 2022-09-27","BTC Map updated_at: 2025-09-18T05:36:30.616Z","OSM: https://www.openstreetmap.org/node/10055182285","lat/lon: 11.977178, 121.9127494"]},{"id":"merchant:jumong-ukay-store:btcmap-place-174","name":"Jumong Ukay Store","source":"btcmap-v4-places","website":null,"country":null,"city":null,"explicit_support":"Jumong Ukay Store is listed in BTC Map as a physical place that accepts Bitcoin.","notes":["BTC Map place id: 174","BTC Map verified_at: 2022-09-28","BTC Map updated_at: 2025-09-18T05:36:30.616Z","OSM: https://www.openstreetmap.org/node/10057376529","lat/lon: 11.9516778, 121.9358477"]},{"id":"merchant:boracay-hairbraid:btcmap-place-196","name":"Boracay Hairbraid","source":"btcmap-v4-places","website":null,"country":null,"city":null,"explicit_support":"Boracay Hairbraid is listed in BTC Map as a physical place that accepts Bitcoin.","notes":["BTC Map place id: 196","BTC Map verified_at: 2022-09-29","BTC Map updated_at: 2025-09-18T05:36:30.616Z","OSM: https://www.openstreetmap.org/node/10059925392","lat/lon: 11.957269, 121.929131"]},{"id":"merchant:estela-tailoring:btcmap-place-202","name":"Estela Tailoring","source":"btcmap-v4-places","website":null,"country":null,"city":null,"explicit_support":"Estela Tailoring is listed in BTC Map as a physical place that accepts Bitcoin.","notes":["BTC Map place id: 202","BTC Map verified_at: 2022-09-29","BTC Map updated_at: 2025-09-18T05:36:30.617Z","OSM: https://www.openstreetmap.org/node/10060080259","lat/lon: 11.9513995, 121.9356459"]},{"id":"merchant:love-tailoring:btcmap-place-204","name":"Love Tailoring","source":"btcmap-v4-places","website":null,"country":null,"city":null,"explicit_support":"Love Tailoring is listed in BTC Map as a physical place that accepts Bitcoin.","notes":["BTC Map place id: 204","BTC Map verified_at: 2022-09-29","BTC Map updated_at: 2025-09-18T05:36:30.617Z","OSM: https://www.openstreetmap.org/node/10060094743","lat/lon: 11.9514327, 121.9356546"]},{"id":"merchant:bogart-cellphone-repair-and-accessories:btcmap-place-205","name":"Bogart Cellphone repair and accessories","source":"btcmap-v4-places","website":null,"country":null,"city":null,"explicit_support":"Bogart Cellphone repair and accessories is listed in BTC Map as a physical place that accepts Bitcoin.","notes":["BTC Map place id: 205","BTC Map verified_at: 2022-09-29","BTC Map updated_at: 2025-09-18T05:36:30.617Z","OSM: https://www.openstreetmap.org/node/10060095126","lat/lon: 11.9532137, 121.9322651"]},{"id":"merchant:fruit-and-vegetable-tw:btcmap-place-207","name":"Fruit And Vegetable TW","source":"btcmap-v4-places","website":null,"country":null,"city":null,"explicit_support":"Fruit And Vegetable TW is listed in BTC Map as a physical place that accepts Bitcoin.","notes":["BTC Map place id: 207","BTC Map verified_at: 2022-09-29","BTC Map updated_at: 2025-09-18T05:36:30.617Z","OSM: https://www.openstreetmap.org/node/10060209589","lat/lon: 11.9516409, 121.9358089"]},{"id":"merchant:mavicamz-produce:btcmap-place-219","name":"Mavicamz Produce","source":"btcmap-v4-places","website":null,"country":null,"city":null,"explicit_support":"Mavicamz Produce is listed in BTC Map as a physical place that accepts Bitcoin.","notes":["BTC Map place id: 219","BTC Map verified_at: 2022-09-30","BTC Map updated_at: 2025-09-18T05:36:30.618Z","OSM: https://www.openstreetmap.org/node/10062685628","lat/lon: 11.9563666, 121.9320283"]},{"id":"merchant:gem-sweet-store:btcmap-place-220","name":"Gem sweet store","source":"btcmap-v4-places","website":null,"country":null,"city":null,"explicit_support":"Gem sweet store is listed in BTC Map as a physical place that accepts Bitcoin.","notes":["BTC Map place id: 220","BTC Map verified_at: 2022-09-30","BTC Map updated_at: 2025-09-18T05:36:30.618Z","OSM: https://www.openstreetmap.org/node/10062685720","lat/lon: 11.9561767, 121.9317562"]},{"id":"merchant:rich-b-seafoods:btcmap-place-233","name":"Rich B Seafoods","source":"btcmap-v4-places","website":null,"country":null,"city":null,"explicit_support":"Rich B Seafoods is listed in BTC Map as a physical place that accepts Bitcoin.","notes":["BTC Map place id: 233","BTC Map verified_at: 2022-09-30","BTC Map updated_at: 2025-09-18T05:36:30.618Z","OSM: https://www.openstreetmap.org/node/10062745421","lat/lon: 11.9564894, 121.9319883"]},{"id":"merchant:ramilyn-store:btcmap-place-235","name":"Ramilyn Store","source":"btcmap-v4-places","website":null,"country":null,"city":null,"explicit_support":"Ramilyn Store is listed in BTC Map as a physical place that accepts Bitcoin.","notes":["BTC Map place id: 235","BTC Map verified_at: 2022-09-30","BTC Map updated_at: 2025-09-18T05:36:30.619Z","OSM: https://www.openstreetmap.org/node/10062749897","lat/lon: 11.9563369, 121.9319827"]},{"id":"merchant:hadiya-souvenir-shop:btcmap-place-458","name":"Hadiya Souvenir Shop","source":"btcmap-v4-places","website":null,"country":null,"city":null,"explicit_support":"Hadiya Souvenir Shop is listed in BTC Map as a physical place that accepts Bitcoin.","notes":["BTC Map place id: 458","BTC Map verified_at: 2022-10-13","BTC Map updated_at: 2025-09-18T05:36:30.619Z","OSM: https://www.openstreetmap.org/node/10099538928","lat/lon: 11.9549382, 121.9289613"]},{"id":"merchant:joel-s-coin-laundry:btcmap-place-1119","name":"Joel's Coin Laundry","source":"btcmap-v4-places","website":null,"country":null,"city":null,"explicit_support":"Joel's Coin Laundry is listed in BTC Map as a physical place that accepts Bitcoin.","notes":["BTC Map place id: 1119","BTC Map verified_at: 2022-11-07","BTC Map updated_at: 2025-09-18T05:36:30.619Z","BTC Map address: 322 NE 38th St Oakland Park 33334","OSM: https://www.openstreetmap.org/node/10167070739","lat/lon: 26.173771, -80.1419723"]},{"id":"merchant:minds-studio:btcmap-place-1120","name":"Minds Studio","source":"btcmap-v4-places","website":"https://mindsstudio.com/","country":null,"city":null,"explicit_support":"Minds Studio is listed in BTC Map as a physical place that accepts Bitcoin.","notes":["BTC Map place id: 1120","BTC Map verified_at: 2022-11-08","BTC Map updated_at: 2025-09-18T05:36:30.619Z","BTC Map address: 130a High Street Crediton EX17 3LQ","OSM: https://www.openstreetmap.org/node/10167709391","lat/lon: 50.7907487, -3.6586173"]},{"id":"merchant:d7-printing-service:btcmap-place-483","name":"D7 Printing Service","source":"btcmap-v4-places","website":null,"country":null,"city":null,"explicit_support":"D7 Printing Service is listed in BTC Map as a physical place that accepts Bitcoin.","notes":["BTC Map place id: 483","BTC Map verified_at: 2022-10-13","BTC Map updated_at: 2025-09-18T05:36:30.62Z","OSM: https://www.openstreetmap.org/node/10099934863","lat/lon: 11.9510082, 121.9397214"]},{"id":"merchant:rechtsanwalt-daniel-dietrich:btcmap-place-5757","name":"Rechtsanwalt Daniel Dietrich","source":"btcmap-v4-places","website":"https://www.anwalt-wst.de","country":null,"city":null,"explicit_support":"Rechtsanwalt Daniel Dietrich is listed in BTC Map as a physical place that accepts Bitcoin.","notes":["BTC Map place id: 5757","BTC Map verified_at: 2022-11-07","BTC Map updated_at: 2025-09-18T05:36:30.62Z","BTC Map address: 10 Gaststraße Westerstede 26655","OSM: https://www.openstreetmap.org/node/1504737798","lat/lon: 53.256854, 7.9303224"]},{"id":"merchant:matilde-parrucchiera:btcmap-place-6346","name":"Matilde Parrucchiera","source":"btcmap-v4-places","website":"https://www.facebook.com/matildeparrucchiera/","country":null,"city":null,"explicit_support":"Matilde Parrucchiera is listed in BTC Map as a physical place that accepts Bitcoin.","notes":["BTC Map place id: 6346","BTC Map verified_at: 2022-11-08","BTC Map updated_at: 2025-09-18T05:36:30.62Z","BTC Map address: Via Cappuccini Crema 26013","OSM: https://www.openstreetmap.org/node/2389503405","lat/lon: 45.3536264, 9.6636353"]},{"id":"merchant:sweet-fruit-store:btcmap-place-488","name":"Sweet Fruit Store","source":"btcmap-v4-places","website":null,"country":null,"city":null,"explicit_support":"Sweet Fruit Store is listed in BTC Map as a physical place that accepts Bitcoin.","notes":["BTC Map place id: 488","BTC Map verified_at: 2022-10-13","BTC Map updated_at: 2025-09-18T05:36:30.621Z","OSM: https://www.openstreetmap.org/node/10099959017","lat/lon: 11.9548476, 121.9337726"]},{"id":"merchant:pisces-and-spices:btcmap-place-596","name":"Pisces and Spices","source":"btcmap-v4-places","website":null,"country":null,"city":null,"explicit_support":"Pisces and Spices is listed in BTC Map as a physical place that accepts Bitcoin.","notes":["BTC Map place id: 596","BTC Map verified_at: 2022-10-13","BTC Map updated_at: 2025-09-18T05:36:30.621Z","OSM: https://www.openstreetmap.org/node/10112922459","lat/lon: 11.9514347, 121.9357371"]},{"id":"merchant:new-empire-pizza-service:btcmap-place-11361","name":"New Empire Pizza Service","source":"btcmap-v4-places","website":"https://www.new-empire-food.de/","country":null,"city":null,"explicit_support":"New Empire Pizza Service is listed in BTC Map as a physical place that accepts Bitcoin.","notes":["BTC Map place id: 11361","BTC Map verified_at: 2022-11-07","BTC Map updated_at: 2025-09-18T05:36:30.621Z","BTC Map address: 87 Kieler Straße Quickborn 25451","OSM: https://www.openstreetmap.org/node/391557771","lat/lon: 53.7310249, 9.8956695"]},{"id":"merchant:healthree-vegetables:btcmap-place-597","name":"HealThree Vegetables","source":"btcmap-v4-places","website":null,"country":null,"city":null,"explicit_support":"HealThree Vegetables is listed in BTC Map as a physical place that accepts Bitcoin.","notes":["BTC Map place id: 597","BTC Map verified_at: 2022-10-13","BTC Map updated_at: 2025-09-18T05:36:30.622Z","OSM: https://www.openstreetmap.org/node/10112932744","lat/lon: 11.9516442, 121.9358733"]},{"id":"merchant:lea-s-baguio-vegetables:btcmap-place-617","name":"Lea's Baguio Vegetables","source":"btcmap-v4-places","website":null,"country":null,"city":null,"explicit_support":"Lea's Baguio Vegetables is listed in BTC Map as a physical place that accepts Bitcoin.","notes":["BTC Map place id: 617","BTC Map verified_at: 2022-10-13","BTC Map updated_at: 2025-09-18T05:36:30.622Z","OSM: https://www.openstreetmap.org/node/10115448971","lat/lon: 11.9514408, 121.9358676"]},{"id":"merchant:mik-s-island-snack:btcmap-place-618","name":"Mik's Island Snack","source":"btcmap-v4-places","website":null,"country":null,"city":null,"explicit_support":"Mik's Island Snack is listed in BTC Map as a physical place that accepts Bitcoin.","notes":["BTC Map place id: 618","BTC Map verified_at: 2022-10-13","BTC Map updated_at: 2025-09-18T05:36:30.622Z","OSM: https://www.openstreetmap.org/node/10115468385","lat/lon: 11.9513975, 121.9357184"]},{"id":"merchant:tirta-spa:btcmap-place-849","name":"Tirta Spa","source":"btcmap-v4-places","website":"https://tirtaspa.com/","country":null,"city":null,"explicit_support":"Tirta Spa is listed in BTC Map as a physical place that accepts Bitcoin.","notes":["BTC Map place id: 849","BTC Map verified_at: 2022-10-13","BTC Map updated_at: 2025-09-18T05:36:30.622Z","OSM: https://www.openstreetmap.org/node/10134750376","lat/lon: 11.9492791, 121.9435496"]},{"id":"merchant:a-and-f-souvenir-shop:btcmap-place-935","name":"A and F Souvenir Shop","source":"btcmap-v4-places","website":null,"country":null,"city":null,"explicit_support":"A and F Souvenir Shop is listed in BTC Map as a physical place that accepts Bitcoin.","notes":["BTC Map place id: 935","BTC Map verified_at: 2022-10-30","BTC Map updated_at: 2025-09-18T05:36:30.623Z","OSM: https://www.openstreetmap.org/node/10139003836","lat/lon: 11.9542562, 121.9314035"]},{"id":"merchant:trixella-travel-and-tours:btcmap-place-939","name":"Trixella Travel and Tours","source":"btcmap-v4-places","website":null,"country":null,"city":null,"explicit_support":"Trixella Travel and Tours is listed in BTC Map as a physical place that accepts Bitcoin.","notes":["BTC Map place id: 939","BTC Map verified_at: 2022-10-30","BTC Map updated_at: 2025-09-18T05:36:30.623Z","OSM: https://www.openstreetmap.org/node/10139007522","lat/lon: 11.951617, 121.9358759"]},{"id":"merchant:dagz-internet-cafe:btcmap-place-943","name":"Dagz Internet Cafe","source":"btcmap-v4-places","website":null,"country":null,"city":null,"explicit_support":"Dagz Internet Cafe is listed in BTC Map as a physical place that accepts Bitcoin.","notes":["BTC Map place id: 943","BTC Map verified_at: 2022-10-30","BTC Map updated_at: 2025-09-18T05:36:30.623Z","OSM: https://www.openstreetmap.org/node/10139015574","lat/lon: 11.9780135, 121.9143903"]},{"id":"merchant:shae-moon:btcmap-place-926","name":"Shae Moon","source":"btcmap-v4-places","website":"https://www.facebook.com/ShaeMoonLLC/","country":null,"city":null,"explicit_support":"Shae Moon is listed in BTC Map as a physical place that accepts Bitcoin.","notes":["BTC Map place id: 926","BTC Map verified_at: 2022-11-18","BTC Map updated_at: 2025-09-18T05:36:30.624Z","OSM: https://www.openstreetmap.org/node/10138711249","lat/lon: 38.8032014, -94.2627613"]},{"id":"merchant:bekid-baby-kids-shop:btcmap-place-1021","name":"BeKid -Baby/Kids Shop","source":"btcmap-v4-places","website":"https://www.bekid.ro/","country":null,"city":null,"explicit_support":"BeKid -Baby/Kids Shop is listed in BTC Map as a physical place that accepts Bitcoin.","notes":["BTC Map place id: 1021","BTC Map verified_at: 2022-11-02","BTC Map updated_at: 2025-09-18T05:36:30.624Z","BTC Map address: Strada 1 Mai Petrești 515850","OSM: https://www.openstreetmap.org/node/10151347914","lat/lon: 45.9372489, 23.5625353"]},{"id":"merchant:prema-delpi:btcmap-place-1190","name":"Prema Delpi","source":"btcmap-v4-places","website":null,"country":null,"city":null,"explicit_support":"Prema Delpi is listed in BTC Map as a physical place that accepts Bitcoin.","notes":["BTC Map place id: 1190","BTC Map verified_at: 2022-11-13","BTC Map updated_at: 2025-09-18T05:36:30.624Z","BTC Map address: 3º Paseo 12 NO Guayaquil","OSM: https://www.openstreetmap.org/node/10181123668","lat/lon: -2.1694776, -79.8959264"]},{"id":"merchant:holiday-house-elvdalsvegen-18-nybergsund-norway:btcmap-place-7463","name":"Holiday house- Elvdalsvegen 18, nybergsund, Norway","source":"btcmap-v4-places","website":"https://ski-norway.webs.com/","country":null,"city":null,"explicit_support":"Holiday house- Elvdalsvegen 18, nybergsund, Norway is listed in BTC Map as a physical place that accepts Bitcoin.","notes":["BTC Map place id: 7463","BTC Map verified_at: 2022-11-04","BTC Map updated_at: 2025-09-18T05:36:30.624Z","OSM: https://www.openstreetmap.org/node/2593897568","lat/lon: 61.258102, 12.326135"]},{"id":"merchant:rygir-as:btcmap-place-1164","name":"Rygir AS","source":"btcmap-v4-places","website":"https://tactx.no","country":null,"city":null,"explicit_support":"Rygir AS is listed in BTC Map as a physical place that accepts Bitcoin.","notes":["BTC Map place id: 1164","BTC Map verified_at: 2022-11-11","BTC Map updated_at: 2025-09-18T05:36:30.625Z","OSM: https://www.openstreetmap.org/node/10176901809","lat/lon: 58.96193, 5.735004"]},{"id":"merchant:juz-juz-dry-goods:btcmap-place-15681","name":"Juz Juz Dry Goods","source":"btcmap-v4-places","website":null,"country":null,"city":null,"explicit_support":"Juz Juz Dry Goods is listed in BTC Map as a physical place that accepts Bitcoin.","notes":["BTC Map place id: 15681","BTC Map verified_at: 2022-09-28","BTC Map updated_at: 2025-09-18T05:36:30.625Z","OSM: https://www.openstreetmap.org/way/502869637","lat/lon: 11.979317250000001, 121.9195531"]},{"id":"merchant:the-house-of-the-traveler:btcmap-place-240","name":"The House Of The Traveler","source":"btcmap-v4-places","website":null,"country":null,"city":null,"explicit_support":"The House Of The Traveler is listed in BTC Map as a physical place that accepts Bitcoin.","notes":["BTC Map place id: 240","BTC Map verified_at: 2022-10-01","BTC Map updated_at: 2025-09-18T05:36:30.626Z","OSM: https://www.openstreetmap.org/node/10067505402","lat/lon: 14.696093, -91.2720978"]},{"id":"merchant:nether-edge-pizza-company:btcmap-place-382","name":"Nether Edge Pizza Company","source":"btcmap-v4-places","website":"https://netheredgepizza.com/","country":null,"city":null,"explicit_support":"Nether Edge Pizza Company is listed in BTC Map as a physical place that accepts Bitcoin.","notes":["BTC Map place id: 382","BTC Map verified_at: 2022-09-10","BTC Map updated_at: 2025-09-18T05:36:30.626Z","OSM: https://www.openstreetmap.org/node/10090567995","lat/lon: 53.3636238, -1.4772947"]},{"id":"merchant:tchi-tchi-coffee:btcmap-place-656","name":"Tchi Tchi coffee","source":"btcmap-v4-places","website":null,"country":null,"city":null,"explicit_support":"Tchi Tchi coffee is listed in BTC Map as a physical place that accepts Bitcoin.","notes":["BTC Map place id: 656","BTC Map verified_at: 2022-10-22","BTC Map updated_at: 2025-09-18T05:36:30.626Z","BTC Map address: Ermou Larnaca 6022","OSM: https://www.openstreetmap.org/node/10121504888","lat/lon: 34.9152961, 33.6340914"]},{"id":"merchant:able-sign:btcmap-place-15974","name":"Able Sign","source":"btcmap-v4-places","website":null,"country":null,"city":null,"explicit_support":"Able Sign is listed in BTC Map as a physical place that accepts Bitcoin.","notes":["BTC Map place id: 15974","BTC Map verified_at: 2022-09-29","BTC Map updated_at: 2025-09-18T05:36:30.626Z","OSM: https://www.openstreetmap.org/way/682182019","lat/lon: 11.954364949999999, 121.93167460000001"]},{"id":"merchant:israel:btcmap-place-990","name":"Israel","source":"btcmap-v4-places","website":null,"country":null,"city":null,"explicit_support":"Israel is listed in BTC Map as a physical place that accepts Bitcoin.","notes":["BTC Map place id: 990","BTC Map verified_at: 2022-10-31","BTC Map updated_at: 2025-09-18T05:36:30.627Z","BTC Map address: 51 Yigal Alon St Tel Aviv-Yafo 61210","OSM: https://www.openstreetmap.org/node/10142636076","lat/lon: 32.1091657, 34.8111176"]},{"id":"merchant:perk-up-coffee-house:btcmap-place-1018","name":"Perk Up Coffee House","source":"btcmap-v4-places","website":"https://www.dailyperkup.com/","country":null,"city":null,"explicit_support":"Perk Up Coffee House is listed in BTC Map as a physical place that accepts Bitcoin.","notes":["BTC Map place id: 1018","BTC Map verified_at: 2022-10-04","BTC Map updated_at: 2025-09-18T05:36:30.628Z","BTC Map address: 1703 West Cameron Avenue Rockdale 76567","OSM: https://www.openstreetmap.org/node/10148040300","lat/lon: 30.6459342, -97.0217315"]},{"id":"merchant:hotel-casa-gozalez:btcmap-place-260","name":"Hotel Casa Gozalez","source":"btcmap-v4-places","website":null,"country":null,"city":null,"explicit_support":"Hotel Casa Gozalez is listed in BTC Map as a physical place that accepts Bitcoin.","notes":["BTC Map place id: 260","BTC Map verified_at: 2022-10-02","BTC Map updated_at: 2025-09-18T05:36:30.629Z","OSM: https://www.openstreetmap.org/node/10069602040","lat/lon: 14.6371623, -91.2311773"]},{"id":"merchant:portside:btcmap-place-6080","name":"Portside","source":"btcmap-v4-places","website":"http://www.portside.fi/","country":null,"city":null,"explicit_support":"Portside is listed in BTC Map as a physical place that accepts Bitcoin.","notes":["BTC Map place id: 6080","BTC Map verified_at: 2022-11-04","BTC Map updated_at: 2025-09-18T05:36:30.629Z","BTC Map address: 8 Stallbacksvägen Dalsbruk 25900","OSM: https://www.openstreetmap.org/node/1977814684","lat/lon: 60.0195136, 22.5062719"]},{"id":"merchant:restaurante-laguna-azul:btcmap-place-13013","name":"Restaurante Laguna Azul","source":"btcmap-v4-places","website":null,"country":null,"city":null,"explicit_support":"Restaurante Laguna Azul is listed in BTC Map as a physical place that accepts Bitcoin.","notes":["BTC Map place id: 13013","BTC Map verified_at: 2022-10-01","BTC Map updated_at: 2025-09-18T05:36:30.629Z","OSM: https://www.openstreetmap.org/node/6173005032","lat/lon: 14.7218052, -91.1361196"]},{"id":"merchant:aloha-resto:btcmap-place-14514","name":"Aloha Resto","source":"btcmap-v4-places","website":"http://www.aloharesto.com/","country":null,"city":null,"explicit_support":"Aloha Resto is listed in BTC Map as a physical place that accepts Bitcoin.","notes":["BTC Map place id: 14514","BTC Map verified_at: 2022-10-15","BTC Map updated_at: 2025-09-18T05:36:30.629Z","BTC Map address: Sumur Melele Teluk Segara Bengkulu City","OSM: https://www.openstreetmap.org/node/9791520174","lat/lon: -3.7944247, 102.2486661"]},{"id":"merchant:cantina-512:btcmap-place-2032","name":"Cantina 512","source":"btcmap-v4-places","website":"https://cantina512.com","country":null,"city":null,"explicit_support":"Cantina 512 is listed in BTC Map as a physical place that accepts Bitcoin.","notes":["BTC Map place id: 2032","BTC Map verified_at: 2022-08-05","BTC Map updated_at: 2025-09-18T05:36:30.63Z","BTC Map address: 70 Rainey Street Austin 78701","OSM: https://www.openstreetmap.org/node/10216293838","lat/lon: 30.2585321, -97.7390007"]},{"id":"merchant:the-tipsy-alchemist:btcmap-place-11330","name":"The Tipsy Alchemist","source":"btcmap-v4-places","website":null,"country":null,"city":null,"explicit_support":"The Tipsy Alchemist is listed in BTC Map as a physical place that accepts Bitcoin.","notes":["BTC Map place id: 11330","BTC Map verified_at: 2022-10-04","BTC Map updated_at: 2025-09-18T05:36:30.63Z","BTC Map address: 70 Rainey Street Austin 78701","OSM: https://www.openstreetmap.org/node/3825447599","lat/lon: 30.258393, -97.739041"]},{"id":"merchant:kfc:btcmap-place-11326","name":"KFC","source":"btcmap-v4-places","website":null,"country":null,"city":null,"explicit_support":"KFC is listed in BTC Map as a physical place that accepts Bitcoin.","notes":["BTC Map place id: 11326","BTC Map verified_at: 2022-11-01","BTC Map updated_at: 2025-09-18T05:36:30.631Z","OSM: https://www.openstreetmap.org/node/3819131771","lat/lon: 13.4624213, -88.1659084"]},{"id":"merchant:1770-marina-cafe:btcmap-place-13939","name":"1770 Marina Cafe","source":"btcmap-v4-places","website":"https://1770marinacafe.com.au/","country":null,"city":null,"explicit_support":"1770 Marina Cafe is listed in BTC Map as a physical place that accepts Bitcoin.","notes":["BTC Map place id: 13939","BTC Map verified_at: 2022-11-14","BTC Map updated_at: 2025-09-18T05:36:30.631Z","BTC Map address: Captain Cook Drive 4677","OSM: https://www.openstreetmap.org/node/8568451017","lat/lon: -24.1719694, 151.883312"]},{"id":"merchant:musikerprogramme:btcmap-place-6892","name":"Musikerprogramme","source":"btcmap-v4-places","website":"http://musikerprogramme.de/","country":null,"city":null,"explicit_support":"Musikerprogramme is listed in BTC Map as a physical place that accepts Bitcoin.","notes":["BTC Map place id: 6892","BTC Map verified_at: 2022-11-03","BTC Map updated_at: 2025-09-18T05:36:30.632Z","BTC Map address: 18 Prinz-Konstantin-Straße 81737","OSM: https://www.openstreetmap.org/node/2552391760","lat/lon: 48.101796, 11.6336843"]},{"id":"merchant:bomb-squad-pooper-scooper:btcmap-place-726","name":"Bomb Squad Pooper Scooper","source":"btcmap-v4-places","website":"https://bombsquadpooperscooper.com/","country":null,"city":null,"explicit_support":"Bomb Squad Pooper Scooper is listed in BTC Map as a physical place that accepts Bitcoin.","notes":["BTC Map place id: 726","BTC Map verified_at: 2022-10-25","BTC Map updated_at: 2025-09-18T05:36:30.633Z","OSM: https://www.openstreetmap.org/node/10127885210","lat/lon: 26.1928391, -80.1155102"]},{"id":"merchant:ez-cleaning-supplies:btcmap-place-795","name":"EZ Cleaning Supplies","source":"btcmap-v4-places","website":null,"country":null,"city":null,"explicit_support":"EZ Cleaning Supplies is listed in BTC Map as a physical place that accepts Bitcoin.","notes":["BTC Map place id: 795","BTC Map verified_at: 2022-10-27","BTC Map updated_at: 2025-09-18T05:36:30.633Z","OSM: https://www.openstreetmap.org/node/10132245572","lat/lon: 25.8459371, -80.3156555"]},{"id":"merchant:bottle-monkey-brew-co:btcmap-place-15811","name":"Bottle Monkey Brew Co","source":"btcmap-v4-places","website":"https://bottlemonkey.im/","country":null,"city":null,"explicit_support":"Bottle Monkey Brew Co is listed in BTC Map as a physical place that accepts Bitcoin.","notes":["BTC Map place id: 15811","BTC Map verified_at: 2022-11-10","BTC Map updated_at: 2025-09-18T05:36:30.633Z","BTC Map address: Farrants Way Castletown IM9 1DQ","OSM: https://www.openstreetmap.org/way/61240313","lat/lon: 54.07278585, -4.6546628000000005"]},{"id":"merchant:martin-lee-sports-and-prestige-ltd:btcmap-place-1195","name":"Martin Lee Sports and Prestige Ltd.","source":"btcmap-v4-places","website":"https://www.martinleegroup.co.uk/","country":null,"city":null,"explicit_support":"Martin Lee Sports and Prestige Ltd. is listed in BTC Map as a physical place that accepts Bitcoin.","notes":["BTC Map place id: 1195","BTC Map verified_at: 2022-11-14","BTC Map updated_at: 2025-09-18T05:36:30.635Z","BTC Map address: Chesterfield S43 4WW","OSM: https://www.openstreetmap.org/node/10183201313","lat/lon: 53.281261, -1.2887311"]},{"id":"merchant:elvila:btcmap-place-15493","name":"Elvila","source":"btcmap-v4-places","website":"https://www.elvila.ro/","country":null,"city":null,"explicit_support":"Elvila is listed in BTC Map as a physical place that accepts Bitcoin.","notes":["BTC Map place id: 15493","BTC Map verified_at: 2022-11-01","BTC Map updated_at: 2025-09-18T05:36:30.635Z","BTC Map address: Strada Siriului București 014352","OSM: https://www.openstreetmap.org/way/38757196","lat/lon: 44.4873866, 26.094891699999998"]},{"id":"merchant:sari-sari-pjds:btcmap-place-237","name":"Sari Sari PJDS","source":"btcmap-v4-places","website":null,"country":null,"city":null,"explicit_support":"Sari Sari PJDS is listed in BTC Map as a physical place that accepts Bitcoin.","notes":["BTC Map place id: 237","BTC Map verified_at: 2022-09-30","BTC Map updated_at: 2025-09-18T05:36:30.636Z","OSM: https://www.openstreetmap.org/node/10062755227","lat/lon: 11.9565243, 121.9319469"]},{"id":"merchant:sari-sari-rosel:btcmap-place-276","name":"Sari-Sari Rosel","source":"btcmap-v4-places","website":null,"country":null,"city":null,"explicit_support":"Sari-Sari Rosel is listed in BTC Map as a physical place that accepts Bitcoin.","notes":["BTC Map place id: 276","BTC Map verified_at: 2022-10-05","BTC Map updated_at: 2025-09-18T05:36:30.636Z","OSM: https://www.openstreetmap.org/node/10076090236","lat/lon: 11.9564832, 121.9319253"]},{"id":"merchant:pukaw-bistro:btcmap-place-375","name":"Pukaw Bistro","source":"btcmap-v4-places","website":null,"country":null,"city":null,"explicit_support":"Pukaw Bistro is listed in BTC Map as a physical place that accepts Bitcoin.","notes":["BTC Map place id: 375","BTC Map verified_at: 2022-10-09","BTC Map updated_at: 2025-09-18T05:36:30.636Z","BTC Map address: General Luna Siargao","OSM: https://www.openstreetmap.org/node/10087649534","lat/lon: 9.7819539, 126.1558791"]},{"id":"merchant:sari-sari-cristy:btcmap-place-282","name":"Sari-Sari Cristy","source":"btcmap-v4-places","website":null,"country":null,"city":null,"explicit_support":"Sari-Sari Cristy is listed in BTC Map as a physical place that accepts Bitcoin.","notes":["BTC Map place id: 282","BTC Map verified_at: 2022-10-05","BTC Map updated_at: 2025-09-18T05:36:30.644Z","OSM: https://www.openstreetmap.org/node/10076118599","lat/lon: 11.956424, 121.932015"]},{"id":"merchant:sari-sari-malou:btcmap-place-293","name":"Sari-Sari Malou","source":"btcmap-v4-places","website":null,"country":null,"city":null,"explicit_support":"Sari-Sari Malou is listed in BTC Map as a physical place that accepts Bitcoin.","notes":["BTC Map place id: 293","BTC Map verified_at: 2022-10-05","BTC Map updated_at: 2025-09-18T05:36:30.645Z","OSM: https://www.openstreetmap.org/node/10076132122","lat/lon: 11.9532792, 121.9377874"]},{"id":"merchant:sari-sari-4d-s-store:btcmap-place-296","name":"Sari-Sari 4D's Store","source":"btcmap-v4-places","website":null,"country":null,"city":null,"explicit_support":"Sari-Sari 4D's Store is listed in BTC Map as a physical place that accepts Bitcoin.","notes":["BTC Map place id: 296","BTC Map verified_at: 2022-10-05","BTC Map updated_at: 2025-09-18T05:36:30.645Z","OSM: https://www.openstreetmap.org/node/10076545970","lat/lon: 11.9578878, 121.9283469"]},{"id":"merchant:kaning-store:btcmap-place-299","name":"Kaning Store","source":"btcmap-v4-places","website":null,"country":null,"city":null,"explicit_support":"Kaning Store is listed in BTC Map as a physical place that accepts Bitcoin.","notes":["BTC Map place id: 299","BTC Map verified_at: 2022-10-05","BTC Map updated_at: 2025-09-18T05:36:30.646Z","OSM: https://www.openstreetmap.org/node/10076563386","lat/lon: 11.9536322, 121.9378451"]},{"id":"merchant:emerald-bay-hotel:btcmap-place-302","name":"Emerald Bay Hotel","source":"btcmap-v4-places","website":"https://www.emeraldislandhotel.net/","country":null,"city":null,"explicit_support":"Emerald Bay Hotel is listed in BTC Map as a physical place that accepts Bitcoin.","notes":["BTC Map place id: 302","BTC Map verified_at: 2022-10-05","BTC Map updated_at: 2025-09-18T05:36:30.646Z","OSM: https://www.openstreetmap.org/node/10076581466","lat/lon: 11.9654837, 121.9227019"]},{"id":"merchant:thaliah-rose-ukay-ukay-clothing:btcmap-place-427","name":"Thaliah Rose Ukay Ukay Clothing","source":"btcmap-v4-places","website":null,"country":null,"city":null,"explicit_support":"Thaliah Rose Ukay Ukay Clothing is listed in BTC Map as a physical place that accepts Bitcoin.","notes":["BTC Map place id: 427","BTC Map verified_at: 2022-10-13","BTC Map updated_at: 2025-09-18T05:36:30.646Z","OSM: https://www.openstreetmap.org/node/10096939687","lat/lon: 11.9782913, 121.918316"]},{"id":"merchant:cycle-360:btcmap-place-16043","name":"Cycle 360","source":"btcmap-v4-places","website":"https://cycle360.com/","country":null,"city":null,"explicit_support":"Cycle 360 is listed in BTC Map as a physical place that accepts Bitcoin.","notes":["BTC Map place id: 16043","BTC Map verified_at: 2022-09-24","BTC Map updated_at: 2025-09-18T05:36:30.646Z","BTC Map address: Isle of Man Business Park Douglas IM2 2QZ","OSM: https://www.openstreetmap.org/way/754867177","lat/lon: 54.153627349999994, -4.53488855"]},{"id":"merchant:heairbraid-and-threading:btcmap-place-436","name":"Heairbraid and threading","source":"btcmap-v4-places","website":null,"country":null,"city":null,"explicit_support":"Heairbraid and threading is listed in BTC Map as a physical place that accepts Bitcoin.","notes":["BTC Map place id: 436","BTC Map verified_at: 2022-10-13","BTC Map updated_at: 2025-09-18T05:36:30.647Z","OSM: https://www.openstreetmap.org/node/10099323173","lat/lon: 11.9624062, 121.9241117"]},{"id":"merchant:anne-rtw-clothing:btcmap-place-469","name":"Anne RTW Clothing","source":"btcmap-v4-places","website":null,"country":null,"city":null,"explicit_support":"Anne RTW Clothing is listed in BTC Map as a physical place that accepts Bitcoin.","notes":["BTC Map place id: 469","BTC Map verified_at: 2022-10-13","BTC Map updated_at: 2025-09-18T05:36:30.647Z","OSM: https://www.openstreetmap.org/node/10099546185","lat/lon: 11.9515215, 121.9357302"]},{"id":"merchant:lacandula-store:btcmap-place-487","name":"Lacandula Store","source":"btcmap-v4-places","website":null,"country":null,"city":null,"explicit_support":"Lacandula Store is listed in BTC Map as a physical place that accepts Bitcoin.","notes":["BTC Map place id: 487","BTC Map verified_at: 2022-10-13","BTC Map updated_at: 2025-09-18T05:36:30.647Z","OSM: https://www.openstreetmap.org/node/10099953928","lat/lon: 11.9569206, 121.9341749"]},{"id":"merchant:lucky-trixy-travel-and-tours:btcmap-place-600","name":"Lucky Trixy Travel And Tours","source":"btcmap-v4-places","website":null,"country":null,"city":null,"explicit_support":"Lucky Trixy Travel And Tours is listed in BTC Map as a physical place that accepts Bitcoin.","notes":["BTC Map place id: 600","BTC Map verified_at: 2022-10-13","BTC Map updated_at: 2025-09-18T05:36:30.647Z","OSM: https://www.openstreetmap.org/node/10112940658","lat/lon: 11.9507096, 121.9351091"]},{"id":"merchant:norjanah-souvenir-shop:btcmap-place-602","name":"Norjanah Souvenir Shop","source":"btcmap-v4-places","website":null,"country":null,"city":null,"explicit_support":"Norjanah Souvenir Shop is listed in BTC Map as a physical place that accepts Bitcoin.","notes":["BTC Map place id: 602","BTC Map verified_at: 2022-10-13","BTC Map updated_at: 2025-09-18T05:36:30.648Z","OSM: https://www.openstreetmap.org/node/10112943284","lat/lon: 11.9542239, 121.9313477"]},{"id":"merchant:simona-flowers-design:btcmap-place-1163","name":"Simona Flowers Design","source":"btcmap-v4-places","website":null,"country":null,"city":null,"explicit_support":"Simona Flowers Design is listed in BTC Map as a physical place that accepts Bitcoin.","notes":["BTC Map place id: 1163","BTC Map verified_at: 2022-11-11","BTC Map updated_at: 2025-09-18T05:36:30.648Z","BTC Map address: 1241 Sable Palm Drive Hollywood 33023","OSM: https://www.openstreetmap.org/node/10176360570","payment_provider: coinos","lat/lon: 25.9884512, -80.2452005"]},{"id":"merchant:tobias-frank-concept-art-and-illustration:btcmap-place-11759","name":"Tobias Frank Concept Art & Illustration","source":"btcmap-v4-places","website":"https://www.conceptartist.de/","country":null,"city":null,"explicit_support":"Tobias Frank Concept Art & Illustration is listed in BTC Map as a physical place that accepts Bitcoin.","notes":["BTC Map place id: 11759","BTC Map verified_at: 2022-11-03","BTC Map updated_at: 2025-09-18T05:36:30.648Z","BTC Map address: 36 Elisabethstraße München 80796","OSM: https://www.openstreetmap.org/node/4610791580","lat/lon: 48.1592432, 11.5683691"]},{"id":"merchant:bricomarche:btcmap-place-15084","name":"Bricomarché","source":"btcmap-v4-places","website":"https://www.brico-meximieux.com/","country":null,"city":null,"explicit_support":"Bricomarché is listed in BTC Map as a physical place that accepts Bitcoin.","notes":["BTC Map place id: 15084","BTC Map verified_at: 2022-11-09","BTC Map updated_at: 2025-09-18T05:36:30.648Z","BTC Map address: Route de Chalamont Meximieux 01800","OSM: https://www.openstreetmap.org/way/233140559","lat/lon: 45.9132605, 5.1919495"]},{"id":"merchant:ferienwohnung-haus-kistenblick:btcmap-place-661","name":"Ferienwohnung 'Haus Kistenblick'","source":"btcmap-v4-places","website":null,"country":null,"city":null,"explicit_support":"Ferienwohnung 'Haus Kistenblick' is listed in BTC Map as a physical place that accepts Bitcoin.","notes":["BTC Map place id: 661","BTC Map verified_at: 2022-10-23","BTC Map updated_at: 2025-09-18T05:36:30.649Z","BTC Map address: 1b Rautstraße Eschenlohe 82438","OSM: https://www.openstreetmap.org/node/10123520074","lat/lon: 47.5914044, 11.1874495"]},{"id":"merchant:body-work-therapies-by-jo:btcmap-place-736","name":"Body Work Therapies By Jo","source":"btcmap-v4-places","website":"https://bodyworktherapiesbyjo.co.uk/","country":null,"city":null,"explicit_support":"Body Work Therapies By Jo is listed in BTC Map as a physical place that accepts Bitcoin.","notes":["BTC Map place id: 736","BTC Map verified_at: 2022-10-25","BTC Map updated_at: 2025-09-18T05:36:30.65Z","BTC Map address: 67 Hilton Road Leeds LS8 4HA","OSM: https://www.openstreetmap.org/node/10128378509","lat/lon: 53.8201685, -1.52061"]},{"id":"merchant:campingzaa:btcmap-place-855","name":"Campingzaa","source":"btcmap-v4-places","website":null,"country":null,"city":null,"explicit_support":"Campingzaa is listed in BTC Map as a physical place that accepts Bitcoin.","notes":["BTC Map place id: 855","BTC Map verified_at: 2022-10-28","BTC Map updated_at: 2025-09-18T05:36:30.65Z","BTC Map address: Wayanad Road Kalpetta 673121","OSM: https://www.openstreetmap.org/node/10134882383","lat/lon: 11.5997982, 76.0808973"]},{"id":"merchant:erin-bike-hut:btcmap-place-14858","name":"Erin Bike Hut","source":"btcmap-v4-places","website":"https://www.erinbikehut.im/","country":null,"city":null,"explicit_support":"Erin Bike Hut is listed in BTC Map as a physical place that accepts Bitcoin.","notes":["BTC Map place id: 14858","BTC Map verified_at: 2022-09-24","BTC Map updated_at: 2025-09-18T05:36:30.65Z","BTC Map address: Station Road Port Erin IM9 6AE","OSM: https://www.openstreetmap.org/way/1210859175","lat/lon: 54.085601249999996, -4.75656745"]},{"id":"merchant:dearne-plumbing-and-bathrooms:btcmap-place-1067","name":"Dearne Plumbing and Bathrooms","source":"btcmap-v4-places","website":"https://www.ddps.biz","country":null,"city":null,"explicit_support":"Dearne Plumbing and Bathrooms is listed in BTC Map as a physical place that accepts Bitcoin.","notes":["BTC Map place id: 1067","BTC Map verified_at: 2022-11-06","BTC Map updated_at: 2025-09-18T05:36:30.651Z","BTC Map address: Muirfield Avenue Mexborough","OSM: https://www.openstreetmap.org/node/10162725408","lat/lon: 53.4844849, -1.306907"]},{"id":"merchant:arcadia-academy:btcmap-place-1064","name":"Arcadia Academy","source":"btcmap-v4-places","website":"https://arcadiaeducation.me/","country":null,"city":null,"explicit_support":"Arcadia Academy is listed in BTC Map as a physical place that accepts Bitcoin.","notes":["BTC Map place id: 1064","BTC Map verified_at: 2022-11-06","BTC Map updated_at: 2025-09-18T05:36:30.652Z","BTC Map address: Ljesevici bb Kotor 85330","OSM: https://www.openstreetmap.org/node/10161926775","lat/lon: 42.3878255, 18.7384933"]},{"id":"merchant:as-cars-leeds-ltd:btcmap-place-1997","name":"AS Cars Leeds Ltd","source":"btcmap-v4-places","website":"https://www.ascarsleedsltd.co.uk/","country":null,"city":null,"explicit_support":"AS Cars Leeds Ltd is listed in BTC Map as a physical place that accepts Bitcoin.","notes":["BTC Map place id: 1997","BTC Map verified_at: 2022-11-17","BTC Map updated_at: 2025-09-18T05:36:30.652Z","BTC Map address: Warm Lane Leeds LS19 7DW","OSM: https://www.openstreetmap.org/node/10196868680","lat/lon: 53.857636, -1.6926161"]},{"id":"merchant:shiner-s-saloon:btcmap-place-5747","name":"Shiner's Saloon","source":"btcmap-v4-places","website":"https://shinerssaloon.com/","country":null,"city":null,"explicit_support":"Shiner's Saloon is listed in BTC Map as a physical place that accepts Bitcoin.","notes":["BTC Map place id: 5747","BTC Map verified_at: 2022-10-04","BTC Map updated_at: 2025-09-18T05:36:30.652Z","BTC Map address: 422 Congress Avenue Austin 78701","OSM: https://www.openstreetmap.org/node/1481721326","lat/lon: 30.2669237, -97.7434785"]},{"id":"merchant:variety-store-boracay:btcmap-place-281","name":"Variety Store Boracay","source":"btcmap-v4-places","website":null,"country":null,"city":null,"explicit_support":"Variety Store Boracay is listed in BTC Map as a physical place that accepts Bitcoin.","notes":["BTC Map place id: 281","BTC Map verified_at: 2022-10-05","BTC Map updated_at: 2025-09-18T05:36:30.653Z","OSM: https://www.openstreetmap.org/node/10076113960","lat/lon: 11.9410803, 121.9394391"]},{"id":"merchant:twin-ap:btcmap-place-284","name":"Twin AP","source":"btcmap-v4-places","website":null,"country":null,"city":null,"explicit_support":"Twin AP is listed in BTC Map as a physical place that accepts Bitcoin.","notes":["BTC Map place id: 284","BTC Map verified_at: 2022-10-05","BTC Map updated_at: 2025-09-18T05:36:30.653Z","OSM: https://www.openstreetmap.org/node/10076120208","lat/lon: 11.9409575, 121.9397326"]},{"id":"merchant:patrickkirkby-com-photography:btcmap-place-7129","name":"PatrickKirkby.com Photography","source":"btcmap-v4-places","website":"https://patrickkirkby.com/","country":null,"city":null,"explicit_support":"PatrickKirkby.com Photography is listed in BTC Map as a physical place that accepts Bitcoin.","notes":["BTC Map place id: 7129","BTC Map verified_at: 2022-11-03","BTC Map updated_at: 2025-09-18T05:36:30.653Z","OSM: https://www.openstreetmap.org/node/2563647289","lat/lon: 54.6028622, 11.9379872"]},{"id":"merchant:sari-sari-gem-s-store:btcmap-place-294","name":"Sari-Sari Gem's Store","source":"btcmap-v4-places","website":null,"country":null,"city":null,"explicit_support":"Sari-Sari Gem's Store is listed in BTC Map as a physical place that accepts Bitcoin.","notes":["BTC Map place id: 294","BTC Map verified_at: 2022-10-05","BTC Map updated_at: 2025-09-18T05:36:30.654Z","OSM: https://www.openstreetmap.org/node/10076174990","lat/lon: 11.945273, 121.9353919"]}]}
