{"format":"compact-registry-v2-seed-batch-v1","verified_at":"2026-04-26","defaults":{"scope":"merchant","acceptance_type":"direct_crypto","supports_program_or_network":"BTC Map / OpenStreetMap","confidence":"low","evidence_kind":"official_store_locator","evidence_publisher":"BTC Map / OpenStreetMap contributors","source_origin":"community_seed","support_rails":[{"rail_id":"asset:bitcoin","rail_type":"asset","label":"Bitcoin"},{"rail_id":"chain:lightning","rail_type":"chain","label":"Lightning Network"}],"notes":["BTC Map is powered by OpenStreetMap/community-maintained location data.","Physical/local merchant seed; verify merchant-side evidence before raising confidence."]},"sources":{"btcmap-v4-places":{"label":"BTC Map REST API v4 places","url":"https://api.btcmap.org/v4/places?fields=id%2Cname%2Clat%2Clon%2Caddress%2Cwebsite%2Cupdated_at%2Cverified_at%2Cosm_id%2Cosm_url%2Cpayment_provider&updated_since=1970-01-01T00%3A00%3A00Z&limit=250","publisher":"BTC Map / OpenStreetMap contributors","kind":"official_store_locator"}},"entries":[{"id":"merchant:different-media:btcmap-place-26892","name":"Different Media","source":"btcmap-v4-places","website":"https://www.differentmedia.ca/","country":null,"city":null,"explicit_support":"Different Media is listed in BTC Map as a physical place that accepts Bitcoin.","notes":["BTC Map place id: 26892","BTC Map place entry has no verified_at value in selected fields.","BTC Map updated_at: 2025-09-18T05:36:30.441Z","OSM: https://www.openstreetmap.org/node/1859659193","lat/lon: 49.6947152, -124.9928343"]},{"id":"merchant:gestora-consultoria-planejamento-e-estrategias:btcmap-place-27498","name":"Gestora consultoria planejamento e estrategias","source":"btcmap-v4-places","website":null,"country":null,"city":null,"explicit_support":"Gestora consultoria planejamento e estrategias is listed in BTC Map as a physical place that accepts Bitcoin.","notes":["BTC Map place id: 27498","BTC Map verified_at: 2025-07-27","BTC Map updated_at: 2025-09-18T05:36:30.441Z","BTC Map address: 1426 D Rua: sete de setembro Chapeco 89801-142","OSM: https://www.openstreetmap.org/node/13030526296","lat/lon: -27.0923538, -52.6029037"]},{"id":"merchant:tia-ryca:btcmap-place-27613","name":"Tia Ryca","source":"btcmap-v4-places","website":null,"country":null,"city":null,"explicit_support":"Tia Ryca is listed in BTC Map as a physical place that accepts Bitcoin.","notes":["BTC Map place id: 27613","BTC Map verified_at: 2025-07-29","BTC Map updated_at: 2025-09-18T05:36:30.441Z","BTC Map address: 113 D Rua Peru Chapecó 89.805-180","OSM: https://www.openstreetmap.org/node/13034900647","lat/lon: -27.0781273, -52.6204826"]},{"id":"merchant:pizza-inn:btcmap-place-24253","name":"Pizza Inn","source":"btcmap-v4-places","website":"https://pizzainn.godaddysites.com/","country":null,"city":null,"explicit_support":"Pizza Inn is listed in BTC Map as a physical place that accepts Bitcoin.","notes":["BTC Map place id: 24253","BTC Map verified_at: 2025-08-11","BTC Map updated_at: 2025-09-18T05:36:30.442Z","BTC Map address: 1 Bahnhofstraße Duderstadt 37115","OSM: https://www.openstreetmap.org/node/5051693971","lat/lon: 51.5077105, 10.2513473"]},{"id":"merchant:bitfiasi-initiative:btcmap-place-28329","name":"Bitfiasi Initiative","source":"btcmap-v4-places","website":"https://bitfiasi.org","country":null,"city":null,"explicit_support":"Bitfiasi Initiative is listed in BTC Map as a physical place that accepts Bitcoin.","notes":["BTC Map place id: 28329","BTC Map verified_at: 2025-08-08","BTC Map updated_at: 2025-09-18T05:36:30.442Z","BTC Map address: Ghanata Street Dodowa","OSM: https://www.openstreetmap.org/node/13062190843","lat/lon: 5.8863428, -0.0941544"]},{"id":"merchant:mountain-house:btcmap-place-28331","name":"Mountain House","source":"btcmap-v4-places","website":"https://www.bedandbreakfast.eu/nl/a/XeQ0i7fAsSE0/mountain-house","country":null,"city":null,"explicit_support":"Mountain House is listed in BTC Map as a physical place that accepts Bitcoin.","notes":["BTC Map place id: 28331","BTC Map verified_at: 2025-08-11","BTC Map updated_at: 2025-09-18T05:36:30.442Z","BTC Map address: 58 Via della Repubblica Rigolato 33020","OSM: https://www.openstreetmap.org/node/13063079676","lat/lon: 46.5497439, 12.8540337"]},{"id":"merchant:het-koffiepand:btcmap-place-24016","name":"Het Koffiepand","source":"btcmap-v4-places","website":"https://koffiepand.nl/","country":null,"city":null,"explicit_support":"Het Koffiepand is listed in BTC Map as a physical place that accepts Bitcoin.","notes":["BTC Map place id: 24016","BTC Map verified_at: 2025-08-08","BTC Map updated_at: 2025-09-18T05:36:30.443Z","BTC Map address: 19 Korte Geere Middelburg 4331LE","OSM: https://www.openstreetmap.org/node/11393886127","lat/lon: 51.4972898, 3.6096965"]},{"id":"merchant:john-shop:btcmap-place-28340","name":"John Shop","source":"btcmap-v4-places","website":null,"country":null,"city":null,"explicit_support":"John Shop is listed in BTC Map as a physical place that accepts Bitcoin.","notes":["BTC Map place id: 28340","BTC Map verified_at: 2025-08-11","BTC Map updated_at: 2025-09-18T05:36:30.443Z","BTC Map address: 52 Gximfiza Crescent Khayelitsha, Cape Town 7784","OSM: https://www.openstreetmap.org/node/13063627418","lat/lon: -34.0408276, 18.6951069"]},{"id":"merchant:mohammad-shop:btcmap-place-28341","name":"Mohammad Shop","source":"btcmap-v4-places","website":null,"country":null,"city":null,"explicit_support":"Mohammad Shop is listed in BTC Map as a physical place that accepts Bitcoin.","notes":["BTC Map place id: 28341","BTC Map verified_at: 2025-08-11","BTC Map updated_at: 2025-09-18T05:36:30.443Z","BTC Map address: 2 Nkcukacha Street Cape Town, Khayelitsha 7784","OSM: https://www.openstreetmap.org/node/13063650262","lat/lon: -34.0414872, 18.6984274"]},{"id":"merchant:fishery:btcmap-place-28342","name":"Fishery","source":"btcmap-v4-places","website":null,"country":null,"city":null,"explicit_support":"Fishery is listed in BTC Map as a physical place that accepts Bitcoin.","notes":["BTC Map place id: 28342","BTC Map verified_at: 2025-08-11","BTC Map updated_at: 2025-09-18T05:36:30.443Z","BTC Map address: 123 Malume Crescent Cape Town, Khayelitsha 7784","OSM: https://www.openstreetmap.org/node/13063675355","lat/lon: -34.0406587, 18.6980352"]},{"id":"merchant:spar-maxi:btcmap-place-28335","name":"SPAR maxi","source":"btcmap-v4-places","website":"https://www.spar.ch/standorte/detail/maxi-grenchen","country":null,"city":null,"explicit_support":"SPAR maxi is listed in BTC Map as a physical place that accepts Bitcoin.","notes":["BTC Map place id: 28335","BTC Map verified_at: 2025-08-11","BTC Map updated_at: 2025-09-18T05:36:30.444Z","BTC Map address: 14 Schmelzistrasse Grenchen 2540","OSM: https://www.openstreetmap.org/node/13054352521","lat/lon: 47.197883, 7.3901632"]},{"id":"merchant:spar-maxi:btcmap-place-28336","name":"SPAR maxi","source":"btcmap-v4-places","website":null,"country":null,"city":null,"explicit_support":"SPAR maxi is listed in BTC Map as a physical place that accepts Bitcoin.","notes":["BTC Map place id: 28336","BTC Map verified_at: 2025-08-11","BTC Map updated_at: 2025-09-18T05:36:30.444Z","BTC Map address: 134 Hohestrasse Oberwil 4104","OSM: https://www.openstreetmap.org/node/13063404767","lat/lon: 47.5203616, 7.551957"]},{"id":"merchant:spar:btcmap-place-28343","name":"Spar","source":"btcmap-v4-places","website":"https://www.spar.ch/standorte/detail/oess-otto","country":null,"city":null,"explicit_support":"Spar is listed in BTC Map as a physical place that accepts Bitcoin.","notes":["BTC Map place id: 28343","BTC Map verified_at: 2025-08-11","BTC Map updated_at: 2025-09-18T05:36:30.444Z","BTC Map address: 22 Alte Staatsstrasse Murg 8877","OSM: https://www.openstreetmap.org/node/418190173","lat/lon: 47.1127297, 9.2141071"]},{"id":"merchant:spar-maxi:btcmap-place-28337","name":"SPAR maxi","source":"btcmap-v4-places","website":null,"country":null,"city":null,"explicit_support":"SPAR maxi is listed in BTC Map as a physical place that accepts Bitcoin.","notes":["BTC Map place id: 28337","BTC Map verified_at: 2025-08-11","BTC Map updated_at: 2025-09-18T05:36:30.445Z","BTC Map address: 112 Zürichstrasse Affoltern am Albis 8910","OSM: https://www.openstreetmap.org/node/13063544737","lat/lon: 47.279259, 8.4541299"]},{"id":"merchant:spar-maxi:btcmap-place-28339","name":"SPAR maxi","source":"btcmap-v4-places","website":null,"country":null,"city":null,"explicit_support":"SPAR maxi is listed in BTC Map as a physical place that accepts Bitcoin.","notes":["BTC Map place id: 28339","BTC Map verified_at: 2025-08-11","BTC Map updated_at: 2025-09-18T05:36:30.445Z","BTC Map address: 23 Hauptstrasse Frieswil 3035","OSM: https://www.openstreetmap.org/node/13063605029","lat/lon: 46.9952729, 7.2849273"]},{"id":"merchant:bella-estetica:btcmap-place-28344","name":"Bella Estetica","source":"btcmap-v4-places","website":null,"country":null,"city":null,"explicit_support":"Bella Estetica is listed in BTC Map as a physical place that accepts Bitcoin.","notes":["BTC Map place id: 28344","BTC Map verified_at: 2025-08-11","BTC Map updated_at: 2025-09-18T05:36:30.445Z","BTC Map address: 5 Via Giovanni Giolitti Pesaro 61122","OSM: https://www.openstreetmap.org/node/13036877299","lat/lon: 43.8958288, 12.9097443"]},{"id":"merchant:pescheria-tognotti:btcmap-place-28289","name":"Pescheria Tognotti","source":"btcmap-v4-places","website":"https://www.pescheriatognotti.it/","country":null,"city":null,"explicit_support":"Pescheria Tognotti is listed in BTC Map as a physical place that accepts Bitcoin.","notes":["BTC Map place id: 28289","BTC Map verified_at: 2025-08-11","BTC Map updated_at: 2025-09-18T05:36:30.446Z","BTC Map address: 4 Via Piomarta Rovereto 38068","OSM: https://www.openstreetmap.org/node/13058140565","lat/lon: 45.8954341, 11.0408092"]},{"id":"merchant:rs-beauty-salon:btcmap-place-28349","name":"RS Beauty Salon","source":"btcmap-v4-places","website":null,"country":null,"city":null,"explicit_support":"RS Beauty Salon is listed in BTC Map as a physical place that accepts Bitcoin.","notes":["BTC Map place id: 28349","BTC Map verified_at: 2025-08-12","BTC Map updated_at: 2025-09-18T05:36:30.449Z","BTC Map address: 7 Tutu Avenue Cape Town, Khayelitsha 7748","OSM: https://www.openstreetmap.org/node/13065429212","lat/lon: -34.0450279, 18.6987048"]},{"id":"merchant:thembisa-car-wash:btcmap-place-28350","name":"Thembisa Car Wash","source":"btcmap-v4-places","website":null,"country":null,"city":null,"explicit_support":"Thembisa Car Wash is listed in BTC Map as a physical place that accepts Bitcoin.","notes":["BTC Map place id: 28350","BTC Map verified_at: 2025-08-12","BTC Map updated_at: 2025-09-18T05:36:30.449Z","BTC Map address: 73 Nyanda Avenue Cape Town, Khayelitsha 7784","OSM: https://www.openstreetmap.org/node/13065464299","lat/lon: -34.0415488, 18.6988609"]},{"id":"merchant:ae-advocacia-e-assessoria-juridica:btcmap-place-28352","name":"AE Advocacia e Assessoria Jurídica","source":"btcmap-v4-places","website":null,"country":null,"city":null,"explicit_support":"AE Advocacia e Assessoria Jurídica is listed in BTC Map as a physical place that accepts Bitcoin.","notes":["BTC Map place id: 28352","BTC Map place entry has no verified_at value in selected fields.","BTC Map updated_at: 2025-09-18T05:36:30.449Z","BTC Map address: 406 Avenida Hilário Pereira de Souza Osasco 06010-170","OSM: https://www.openstreetmap.org/node/13065516673","lat/lon: -23.5341082, -46.7706465"]},{"id":"merchant:ojos-del-mar-eye-care-clinic:btcmap-place-25088","name":"Ojos del Mar - Eye Care Clinic","source":"btcmap-v4-places","website":null,"country":null,"city":null,"explicit_support":"Ojos del Mar - Eye Care Clinic is listed in BTC Map as a physical place that accepts Bitcoin.","notes":["BTC Map place id: 25088","BTC Map verified_at: 2025-08-12","BTC Map updated_at: 2025-09-18T05:36:30.45Z","OSM: https://www.openstreetmap.org/node/12778900885","lat/lon: 10.3082906, -85.8308881"]},{"id":"merchant:eye-spy-escape-rooms:btcmap-place-28353","name":"Eye Spy escape rooms","source":"btcmap-v4-places","website":"https://eyespyescaperoom.com/","country":null,"city":null,"explicit_support":"Eye Spy escape rooms is listed in BTC Map as a physical place that accepts Bitcoin.","notes":["BTC Map place id: 28353","BTC Map verified_at: 2025-08-12","BTC Map updated_at: 2025-09-18T05:36:30.45Z","BTC Map address: 1401 South Danville Drive Abilene 79605","OSM: https://www.openstreetmap.org/node/13065749498","lat/lon: 32.4277112, -99.7838878"]},{"id":"merchant:estudio-fotografico-nanos:btcmap-place-28354","name":"Estudio Fotográfico Nanos","source":"btcmap-v4-places","website":null,"country":null,"city":null,"explicit_support":"Estudio Fotográfico Nanos is listed in BTC Map as a physical place that accepts Bitcoin.","notes":["BTC Map place id: 28354","BTC Map verified_at: 2025-08-12","BTC Map updated_at: 2025-09-18T05:36:30.451Z","BTC Map address: 191 Calle Pando Potosí","OSM: https://www.openstreetmap.org/node/13065639494","lat/lon: -19.5783313, -65.7536677"]},{"id":"merchant:rung-aroon-coffee-bar:btcmap-place-24182","name":"Rung Aroon Coffee Bar","source":"btcmap-v4-places","website":null,"country":null,"city":null,"explicit_support":"Rung Aroon Coffee Bar is listed in BTC Map as a physical place that accepts Bitcoin.","notes":["BTC Map place id: 24182","BTC Map verified_at: 2025-08-13","BTC Map updated_at: 2025-09-18T05:36:30.453Z","BTC Map address: 21/17 งามวงศ์วาน 56 10900","OSM: https://www.openstreetmap.org/node/12622284690","lat/lon: 13.841005, 100.5727981"]},{"id":"merchant:noodles:btcmap-place-28313","name":"Noodles","source":"btcmap-v4-places","website":null,"country":null,"city":null,"explicit_support":"Noodles is listed in BTC Map as a physical place that accepts Bitcoin.","notes":["BTC Map place id: 28313","BTC Map verified_at: 2025-08-13","BTC Map updated_at: 2025-09-18T05:36:30.453Z","BTC Map address: ถนน บุญฑริกจักรพงษ์ 46110","OSM: https://www.openstreetmap.org/node/13061344217","lat/lon: 16.5460053, 104.055228"]},{"id":"merchant::btcmap-place-24590","name":"ข้าวมันไก่สามเซียนพิษณุโลก","source":"btcmap-v4-places","website":null,"country":null,"city":null,"explicit_support":"ข้าวมันไก่สามเซียนพิษณุโลก is listed in BTC Map as a physical place that accepts Bitcoin.","notes":["BTC Map place id: 24590","BTC Map verified_at: 2025-08-13","BTC Map updated_at: 2025-09-18T05:36:30.454Z","BTC Map address: 57, 54 ถนน พระองค์ดำ 65000","OSM: https://www.openstreetmap.org/node/12696681569","lat/lon: 16.8205263, 100.268798"]},{"id":"merchant:jack-the-reaper:btcmap-place-26144","name":"Jack The Reaper","source":"btcmap-v4-places","website":null,"country":null,"city":null,"explicit_support":"Jack The Reaper is listed in BTC Map as a physical place that accepts Bitcoin.","notes":["BTC Map place id: 26144","BTC Map verified_at: 2025-08-13","BTC Map updated_at: 2025-09-18T05:36:30.454Z","BTC Map address: 170/1 ถนนบ้านดำ 57100","OSM: https://www.openstreetmap.org/node/12860331935","lat/lon: 19.99235, 99.8602687"]},{"id":"merchant:sisterhood-cafe:btcmap-place-28314","name":"sisterhood.cafe","source":"btcmap-v4-places","website":null,"country":null,"city":null,"explicit_support":"sisterhood.cafe is listed in BTC Map as a physical place that accepts Bitcoin.","notes":["BTC Map place id: 28314","BTC Map verified_at: 2025-08-10","BTC Map updated_at: 2025-09-18T05:36:30.454Z","BTC Map address: 53/75 ซอย สันติธรรม 2 บางม่วง 11140","OSM: https://www.openstreetmap.org/node/8355290841","lat/lon: 13.8268083, 100.3751502"]},{"id":"merchant:wachoma:btcmap-place-28357","name":"Wachoma","source":"btcmap-v4-places","website":null,"country":null,"city":null,"explicit_support":"Wachoma is listed in BTC Map as a physical place that accepts Bitcoin.","notes":["BTC Map place id: 28357","BTC Map verified_at: 2025-08-16","BTC Map updated_at: 2025-09-18T05:36:30.454Z","BTC Map address: T3-T5 Gximfiza Crescent Cape Town, Khayelitsha 7784","OSM: https://www.openstreetmap.org/node/13068062578","lat/lon: -34.042654, 18.6984268"]},{"id":"merchant:five-star:btcmap-place-25379","name":"Five Star","source":"btcmap-v4-places","website":"https://fivestar.in.th/","country":null,"city":null,"explicit_support":"Five Star is listed in BTC Map as a physical place that accepts Bitcoin.","notes":["BTC Map place id: 25379","BTC Map verified_at: 2025-08-13","BTC Map updated_at: 2025-09-18T05:36:30.455Z","BTC Map address: อยู่เจริญ 4 ถนนไสวประชาราษฎร์ 12150","OSM: https://www.openstreetmap.org/node/12818578388","lat/lon: 13.9539438, 100.6848772"]},{"id":"merchant:unh-cafe-and-craft:btcmap-place-28330","name":"unh Cafe & Craft","source":"btcmap-v4-places","website":null,"country":null,"city":null,"explicit_support":"unh Cafe & Craft is listed in BTC Map as a physical place that accepts Bitcoin.","notes":["BTC Map place id: 28330","BTC Map verified_at: 2025-08-13","BTC Map updated_at: 2025-09-18T05:36:30.455Z","BTC Map address: 39 Moo 11 50150","OSM: https://www.openstreetmap.org/node/13062546004","lat/lon: 19.1919813, 98.980873"]},{"id":"merchant:5:btcmap-place-23651","name":"ก๋วยเตี๋ยว​เรือ​ชามทอง รังสิต คลอง 5","source":"btcmap-v4-places","website":null,"country":null,"city":null,"explicit_support":"ก๋วยเตี๋ยว​เรือ​ชามทอง รังสิต คลอง 5 is listed in BTC Map as a physical place that accepts Bitcoin.","notes":["BTC Map place id: 23651","BTC Map verified_at: 2025-08-13","BTC Map updated_at: 2025-09-18T05:36:30.456Z","BTC Map address: 10/12 ถนนรังสิต-นครนายก 12120","OSM: https://www.openstreetmap.org/node/12548626104","lat/lon: 14.0055976, 100.6991756"]},{"id":"merchant:1000:btcmap-place-24978","name":"คลังยาอาม่า - ตลาดอาม่า1000สุข","source":"btcmap-v4-places","website":null,"country":null,"city":null,"explicit_support":"คลังยาอาม่า - ตลาดอาม่า1000สุข is listed in BTC Map as a physical place that accepts Bitcoin.","notes":["BTC Map place id: 24978","BTC Map verified_at: 2025-08-13","BTC Map updated_at: 2025-09-18T05:36:30.456Z","BTC Map address: 64/1 ถนนธัญบุรี-วังน้อย 12120","OSM: https://www.openstreetmap.org/node/12760942330","lat/lon: 14.0490587, 100.7471647"]},{"id":"merchant:pick-n-pay-liquor:btcmap-place-27929","name":"Pick n Pay Liquor","source":"btcmap-v4-places","website":null,"country":null,"city":null,"explicit_support":"Pick n Pay Liquor is listed in BTC Map as a physical place that accepts Bitcoin.","notes":["BTC Map place id: 27929","BTC Map verified_at: 2025-08-01","BTC Map updated_at: 2025-09-18T05:36:30.457Z","OSM: https://www.openstreetmap.org/node/1146830229","lat/lon: -34.0702841, 18.8225783"]},{"id":"merchant:pick-n-pay-liquor:btcmap-place-27969","name":"Pick n Pay Liquor","source":"btcmap-v4-places","website":null,"country":null,"city":null,"explicit_support":"Pick n Pay Liquor is listed in BTC Map as a physical place that accepts Bitcoin.","notes":["BTC Map place id: 27969","BTC Map verified_at: 2025-08-01","BTC Map updated_at: 2025-09-18T05:36:30.457Z","OSM: https://www.openstreetmap.org/node/4822704362","lat/lon: -34.0878063, 18.4817739"]},{"id":"merchant:pick-n-pay-liquor:btcmap-place-27998","name":"Pick n Pay Liquor","source":"btcmap-v4-places","website":null,"country":null,"city":null,"explicit_support":"Pick n Pay Liquor is listed in BTC Map as a physical place that accepts Bitcoin.","notes":["BTC Map place id: 27998","BTC Map verified_at: 2025-08-01","BTC Map updated_at: 2025-09-18T05:36:30.457Z","OSM: https://www.openstreetmap.org/node/11482443601","lat/lon: -32.9214761, 17.9864839"]},{"id":"merchant:beck-and-bulow:btcmap-place-23371","name":"Beck and Bulow","source":"btcmap-v4-places","website":null,"country":null,"city":null,"explicit_support":"Beck and Bulow is listed in BTC Map as a physical place that accepts Bitcoin.","notes":["BTC Map place id: 23371","BTC Map verified_at: 2025-08-14","BTC Map updated_at: 2025-09-18T05:36:30.53Z","BTC Map address: 1934 Cerrillos Road","OSM: https://www.openstreetmap.org/node/12077566462","lat/lon: 35.6633306, -105.9753402"]},{"id":"merchant:pomar-marins:btcmap-place-28367","name":"Pomar Marins","source":"btcmap-v4-places","website":null,"country":null,"city":null,"explicit_support":"Pomar Marins is listed in BTC Map as a physical place that accepts Bitcoin.","notes":["BTC Map place id: 28367","BTC Map verified_at: 2025-08-13","BTC Map updated_at: 2025-09-18T05:36:30.53Z","BTC Map address: Rolante 95690-000","OSM: https://www.openstreetmap.org/node/13069741832","lat/lon: -29.6832156, -50.5798679"]},{"id":"merchant:urban-stay-sofia:btcmap-place-28371","name":"Urban Stay Sofia","source":"btcmap-v4-places","website":"https://maps.app.goo.gl/pqin3Ko6AJMnSKwT9","country":null,"city":null,"explicit_support":"Urban Stay Sofia is listed in BTC Map as a physical place that accepts Bitcoin.","notes":["BTC Map place id: 28371","BTC Map verified_at: 2025-08-14","BTC Map updated_at: 2025-09-18T05:36:30.532Z","BTC Map address: 19 Панагюрище София 1202","OSM: https://www.openstreetmap.org/way/377667779","lat/lon: 42.7056867, 23.329281"]},{"id":"merchant:flat-lizard:btcmap-place-28374","name":"Flat Lizard","source":"btcmap-v4-places","website":null,"country":null,"city":null,"explicit_support":"Flat Lizard is listed in BTC Map as a physical place that accepts Bitcoin.","notes":["BTC Map place id: 28374","BTC Map verified_at: 2025-08-14","BTC Map updated_at: 2025-09-18T05:36:30.532Z","BTC Map address: Shop 5, Houtappel Building, Main Service Road Sedgefield 6573","OSM: https://www.openstreetmap.org/node/13070945381","lat/lon: -34.0155119, 22.8064064"]},{"id":"merchant:207-barbers:btcmap-place-25382","name":"207 Barbers","source":"btcmap-v4-places","website":null,"country":null,"city":null,"explicit_support":"207 Barbers is listed in BTC Map as a physical place that accepts Bitcoin.","notes":["BTC Map place id: 25382","BTC Map verified_at: 2025-08-14","BTC Map updated_at: 2025-09-18T05:36:30.533Z","BTC Map address: 207 Manford Way Chigwell IG7 4DJ","OSM: https://www.openstreetmap.org/node/4654216341","lat/lon: 51.6083119, 0.1073806"]},{"id":"merchant:spar:btcmap-place-26594","name":"Spar","source":"btcmap-v4-places","website":"https://www.spar.ch/standorte/detail/sm-niederhasli","country":null,"city":null,"explicit_support":"Spar is listed in BTC Map as a physical place that accepts Bitcoin.","notes":["BTC Map place id: 26594","BTC Map verified_at: 2025-08-14","BTC Map updated_at: 2025-09-18T05:36:30.533Z","BTC Map address: 54 Mandachstrasse Niederhasli 8155","OSM: https://www.openstreetmap.org/node/4316877028","lat/lon: 47.4800641, 8.4902303"]},{"id":"merchant:digitaltek-celulares:btcmap-place-28375","name":"DigitalTek Celulares","source":"btcmap-v4-places","website":null,"country":null,"city":null,"explicit_support":"DigitalTek Celulares is listed in BTC Map as a physical place that accepts Bitcoin.","notes":["BTC Map place id: 28375","BTC Map verified_at: 2025-08-14","BTC Map updated_at: 2025-09-18T05:36:30.533Z","BTC Map address: Rua José Maria Veras Camocim 62400000","OSM: https://www.openstreetmap.org/node/13071272789","lat/lon: -2.8956131, -40.8430129"]},{"id":"merchant:soff-perfumes:btcmap-place-28376","name":"Soff perfumes","source":"btcmap-v4-places","website":"http://www.soff.com.br/","country":null,"city":null,"explicit_support":"Soff perfumes is listed in BTC Map as a physical place that accepts Bitcoin.","notes":["BTC Map place id: 28376","BTC Map verified_at: 2025-08-14","BTC Map updated_at: 2025-09-18T05:36:30.533Z","BTC Map address: 251 -1052 Avenida República do Líbano Recife - PE 51110-150","OSM: https://www.openstreetmap.org/node/13071335479","lat/lon: -8.0868021, -34.8936295"]},{"id":"merchant:r-and-d-phone-reparation:btcmap-place-24704","name":"R&D Phone Reparation","source":"btcmap-v4-places","website":null,"country":null,"city":null,"explicit_support":"R&D Phone Reparation is listed in BTC Map as a physical place that accepts Bitcoin.","notes":["BTC Map place id: 24704","BTC Map verified_at: 2024-08-15","BTC Map updated_at: 2025-09-18T05:36:30.534Z","BTC Map address: 1 Lachmanstraat Latour","OSM: https://www.openstreetmap.org/node/12712790650","lat/lon: 5.7945159, -55.1824354"]},{"id":"merchant:stonk-s-barbearia:btcmap-place-28377","name":"Stonk's Barbearia","source":"btcmap-v4-places","website":"https://www.app.frizzar.com.br/p/barbeariastonks","country":null,"city":null,"explicit_support":"Stonk's Barbearia is listed in BTC Map as a physical place that accepts Bitcoin.","notes":["BTC Map place id: 28377","BTC Map verified_at: 2025-08-14","BTC Map updated_at: 2025-09-18T05:36:30.534Z","BTC Map address: 475 Rua das chácaras Belo Horizonte 31680320","OSM: https://www.openstreetmap.org/node/13071366175","lat/lon: -19.7975111, -43.9901462"]},{"id":"merchant:angels-copie:btcmap-place-24711","name":"Angels Copie","source":"btcmap-v4-places","website":null,"country":null,"city":null,"explicit_support":"Angels Copie is listed in BTC Map as a physical place that accepts Bitcoin.","notes":["BTC Map place id: 24711","BTC Map verified_at: 2024-08-15","BTC Map updated_at: 2025-09-18T05:36:30.535Z","BTC Map address: Dr. Sophie Redmondstraat Paramaribo","OSM: https://www.openstreetmap.org/node/12712969264","lat/lon: 5.8251946, -55.1636999"]},{"id":"merchant:g-and-g-imports-and-more:btcmap-place-24712","name":"G & G Imports and More","source":"btcmap-v4-places","website":null,"country":null,"city":null,"explicit_support":"G & G Imports and More is listed in BTC Map as a physical place that accepts Bitcoin.","notes":["BTC Map place id: 24712","BTC Map verified_at: 2024-08-15","BTC Map updated_at: 2025-09-18T05:36:30.535Z","BTC Map address: Dr. Sophie Redmondstraat Paramaribo","OSM: https://www.openstreetmap.org/node/12712988650","lat/lon: 5.8258105, -55.163237"]},{"id":"merchant:reomi-beauty-salon:btcmap-place-24713","name":"Reomi Beauty Salon","source":"btcmap-v4-places","website":null,"country":null,"city":null,"explicit_support":"Reomi Beauty Salon is listed in BTC Map as a physical place that accepts Bitcoin.","notes":["BTC Map place id: 24713","BTC Map verified_at: 2024-08-15","BTC Map updated_at: 2025-09-18T05:36:30.535Z","BTC Map address: Dr. Sophie Redmondstraat Paramaribo","OSM: https://www.openstreetmap.org/node/12712945198","lat/lon: 5.825619, -55.1633853"]},{"id":"merchant:prometheus-regenerative-lab:btcmap-place-28379","name":"Prometheus Regenerative Lab","source":"btcmap-v4-places","website":"https://www.yntieusebiomd.com/","country":null,"city":null,"explicit_support":"Prometheus Regenerative Lab is listed in BTC Map as a physical place that accepts Bitcoin.","notes":["BTC Map place id: 28379","BTC Map verified_at: 2025-08-15","BTC Map updated_at: 2025-09-18T05:36:30.535Z","BTC Map address: 2 Calle Toledo San Pedro de Macorís 21000","OSM: https://www.openstreetmap.org/node/13071762741","lat/lon: 18.4797679, -69.3086541"]},{"id":"merchant:appartamento-marini:btcmap-place-27251","name":"Appartamento Marini","source":"btcmap-v4-places","website":"https://airbnb.com/h/casa-vacanza-lido-marini","country":null,"city":null,"explicit_support":"Appartamento Marini is listed in BTC Map as a physical place that accepts Bitcoin.","notes":["BTC Map place id: 27251","BTC Map verified_at: 2025-08-15","BTC Map updated_at: 2025-09-18T05:36:30.536Z","BTC Map address: 8 Via Duca degli Abruzzi Ugento 73050","OSM: https://www.openstreetmap.org/node/13009049634","lat/lon: 39.8509725, 18.1838981"]},{"id":"merchant:dhanashree-salone:btcmap-place-28381","name":"Dhanashree Salone","source":"btcmap-v4-places","website":null,"country":null,"city":null,"explicit_support":"Dhanashree Salone is listed in BTC Map as a physical place that accepts Bitcoin.","notes":["BTC Map place id: 28381","BTC Map verified_at: 2025-08-15","BTC Map updated_at: 2025-09-18T05:36:30.536Z","BTC Map address: Dr. Bhaisaheb Chitnis Road Khed 415709","OSM: https://www.openstreetmap.org/node/13072238735","lat/lon: 17.7193923, 73.3956678"]},{"id":"merchant:verve:btcmap-place-28382","name":"Verve","source":"btcmap-v4-places","website":"https://www.vervebar.co.uk/","country":null,"city":null,"explicit_support":"Verve is listed in BTC Map as a physical place that accepts Bitcoin.","notes":["BTC Map place id: 28382","BTC Map verified_at: 2025-08-15","BTC Map updated_at: 2025-09-18T05:36:30.536Z","BTC Map address: 1-2 Woolhall Street Bury St Edmunds IP33 1LA","OSM: https://www.openstreetmap.org/node/5482092189","lat/lon: 52.2450516, 0.71121"]},{"id":"merchant:coffee-company-rk-biz-center:btcmap-place-24007","name":"Coffee Company - RK Biz Center","source":"btcmap-v4-places","website":"https://www.coffeecompany.asia/","country":null,"city":null,"explicit_support":"Coffee Company - RK Biz Center is listed in BTC Map as a physical place that accepts Bitcoin.","notes":["BTC Map place id: 24007","BTC Map verified_at: 2025-08-15","BTC Map updated_at: 2025-09-18T05:36:30.537Z","BTC Map address: 36/54 ถนนกรุงเทพฯ-ชลบุรี 10520","OSM: https://www.openstreetmap.org/node/12600858098","lat/lon: 13.7303766, 100.7324716"]},{"id":"merchant:saskoshop:btcmap-place-28221","name":"SaskoShop","source":"btcmap-v4-places","website":null,"country":null,"city":null,"explicit_support":"SaskoShop is listed in BTC Map as a physical place that accepts Bitcoin.","notes":["BTC Map place id: 28221","BTC Map verified_at: 2025-08-16","BTC Map updated_at: 2025-09-18T05:36:30.539Z","BTC Map address: Ntsikana Street Mossel Bay Local Municipality 6500","OSM: https://www.openstreetmap.org/node/13048222567","lat/lon: -34.1807355, 22.1046609"]},{"id":"merchant:daniel-pecas-eletricas:btcmap-place-28397","name":"Daniel Peças Elétricas","source":"btcmap-v4-places","website":null,"country":null,"city":null,"explicit_support":"Daniel Peças Elétricas is listed in BTC Map as a physical place that accepts Bitcoin.","notes":["BTC Map place id: 28397","BTC Map verified_at: 2025-08-16","BTC Map updated_at: 2025-09-18T05:36:30.539Z","BTC Map address: 85 Estrada da Cachamorra Rio de Janeiro 23040-151","OSM: https://www.openstreetmap.org/node/13073366249","lat/lon: -22.9151905, -43.5497647"]},{"id":"merchant:footprint-preschool-and-aftercare:btcmap-place-25363","name":"Footprint Preschool and Aftercare","source":"btcmap-v4-places","website":null,"country":null,"city":null,"explicit_support":"Footprint Preschool and Aftercare is listed in BTC Map as a physical place that accepts Bitcoin.","notes":["BTC Map place id: 25363","BTC Map verified_at: 2025-08-16","BTC Map updated_at: 2025-09-18T05:36:30.54Z","BTC Map address: L. Mpetshwa Street Mossel Bay Local Municipality 6500","OSM: https://www.openstreetmap.org/node/12816957144","lat/lon: -34.1697418, 22.1128527"]},{"id":"merchant:otoni-imoveis:btcmap-place-28391","name":"Otoni Imóveis","source":"btcmap-v4-places","website":null,"country":null,"city":null,"explicit_support":"Otoni Imóveis is listed in BTC Map as a physical place that accepts Bitcoin.","notes":["BTC Map place id: 28391","BTC Map verified_at: 2025-08-15","BTC Map updated_at: 2025-09-18T05:36:30.54Z","BTC Map address: Av. Juscelino Kubitschek Pimenta 35585-000","OSM: https://www.openstreetmap.org/node/13073215158","lat/lon: -20.4808452, -45.801937"]},{"id":"merchant:morya-holidays:btcmap-place-28400","name":"Morya Holidays","source":"btcmap-v4-places","website":null,"country":null,"city":null,"explicit_support":"Morya Holidays is listed in BTC Map as a physical place that accepts Bitcoin.","notes":["BTC Map place id: 28400","BTC Map place entry has no verified_at value in selected fields.","BTC Map updated_at: 2025-09-18T05:36:30.54Z","OSM: https://www.openstreetmap.org/node/13073713607","lat/lon: 17.7198799, 73.3985566"]},{"id":"merchant:ka-la-coffee:btcmap-place-25356","name":"KA-LA Coffee","source":"btcmap-v4-places","website":null,"country":null,"city":null,"explicit_support":"KA-LA Coffee is listed in BTC Map as a physical place that accepts Bitcoin.","notes":["BTC Map place id: 25356","BTC Map verified_at: 2025-08-16","BTC Map updated_at: 2025-09-18T05:36:30.541Z","BTC Map address: 130/12 12110","OSM: https://www.openstreetmap.org/node/12808883030","lat/lon: 14.0346785, 100.7324022"]},{"id":"merchant:chit-hole-surawong:btcmap-place-24287","name":"Chit Hole Surawong","source":"btcmap-v4-places","website":"https://chitholding.com/","country":null,"city":null,"explicit_support":"Chit Hole Surawong is listed in BTC Map as a physical place that accepts Bitcoin.","notes":["BTC Map place id: 24287","BTC Map verified_at: 2025-08-16","BTC Map updated_at: 2025-09-18T05:36:30.542Z","BTC Map address: 54 ถนนสุรวงศ์ 10500","OSM: https://www.openstreetmap.org/node/12640894703","lat/lon: 13.7300773, 100.5315367"]},{"id":"merchant:chit-hole-rangsit-rooftop:btcmap-place-24390","name":"Chit Hole Rangsit Rooftop","source":"btcmap-v4-places","website":"https://chitholding.com/","country":null,"city":null,"explicit_support":"Chit Hole Rangsit Rooftop is listed in BTC Map as a physical place that accepts Bitcoin.","notes":["BTC Map place id: 24390","BTC Map verified_at: 2025-08-16","BTC Map updated_at: 2025-09-18T05:36:30.542Z","BTC Map address: ซอยรังสิต-นครนายก 14 12130","OSM: https://www.openstreetmap.org/node/12658170647","lat/lon: 13.9852831, 100.625787"]},{"id":"merchant:the-libreria-cafe:btcmap-place-28315","name":"The Libreria Cafe","source":"btcmap-v4-places","website":null,"country":null,"city":null,"explicit_support":"The Libreria Cafe is listed in BTC Map as a physical place that accepts Bitcoin.","notes":["BTC Map place id: 28315","BTC Map verified_at: 2025-08-10","BTC Map updated_at: 2025-09-18T05:36:30.542Z","BTC Map address: 799 Unipark 30000","OSM: https://www.openstreetmap.org/node/13061349632","lat/lon: 14.9083453, 102.0123862"]},{"id":"merchant:oficina-do-xuxu:btcmap-place-28387","name":"Oficina do XuXu","source":"btcmap-v4-places","website":null,"country":null,"city":null,"explicit_support":"Oficina do XuXu is listed in BTC Map as a physical place that accepts Bitcoin.","notes":["BTC Map place id: 28387","BTC Map verified_at: 2025-08-17","BTC Map updated_at: 2025-09-18T05:36:30.543Z","BTC Map address: 247 Rua Olinto Fonseca Pimenta 35585000","OSM: https://www.openstreetmap.org/node/13072642455","lat/lon: -20.4731498, -45.8019833"]},{"id":"merchant:icar-auto-center:btcmap-place-28388","name":"ICAR Auto Center","source":"btcmap-v4-places","website":null,"country":null,"city":null,"explicit_support":"ICAR Auto Center is listed in BTC Map as a physical place that accepts Bitcoin.","notes":["BTC Map place id: 28388","BTC Map verified_at: 2025-08-17","BTC Map updated_at: 2025-09-18T05:36:30.543Z","BTC Map address: 353 Rua Olinto Fonseca Pimenta 35585000","OSM: https://www.openstreetmap.org/node/13072600768","lat/lon: -20.4722844, -45.8022397"]},{"id":"merchant:miller-moto-center:btcmap-place-28389","name":"Miller Moto Center","source":"btcmap-v4-places","website":null,"country":null,"city":null,"explicit_support":"Miller Moto Center is listed in BTC Map as a physical place that accepts Bitcoin.","notes":["BTC Map place id: 28389","BTC Map verified_at: 2025-08-17","BTC Map updated_at: 2025-09-18T05:36:30.543Z","BTC Map address: 650 Rua Olinto Fonseca Pimenta 35585000","OSM: https://www.openstreetmap.org/node/13072705016","lat/lon: -20.4711671, -45.8027254"]},{"id":"merchant:jci-esquadrias-de-aluminio:btcmap-place-28383","name":"JCI Esquadrias de Alumínio","source":"btcmap-v4-places","website":null,"country":null,"city":null,"explicit_support":"JCI Esquadrias de Alumínio is listed in BTC Map as a physical place that accepts Bitcoin.","notes":["BTC Map place id: 28383","BTC Map verified_at: 2025-08-17","BTC Map updated_at: 2025-09-18T05:36:30.544Z","BTC Map address: 920 Rua Elso Previtale Valinhos 13272-300","OSM: https://www.openstreetmap.org/node/13072416554","lat/lon: -22.955259, -46.9999283"]},{"id":"merchant:auto-pecas-lopes:btcmap-place-28386","name":"Auto Peças Lopes","source":"btcmap-v4-places","website":null,"country":null,"city":null,"explicit_support":"Auto Peças Lopes is listed in BTC Map as a physical place that accepts Bitcoin.","notes":["BTC Map place id: 28386","BTC Map verified_at: 2025-08-17","BTC Map updated_at: 2025-09-18T05:36:30.544Z","BTC Map address: 344 Rua Olinto Fonseca Pimenta 35585000","OSM: https://www.openstreetmap.org/node/13072591985","lat/lon: -20.4723291, -45.8024023"]},{"id":"merchant:papa-rizz-healthy-living:btcmap-place-28403","name":"Papa rizz healthy living","source":"btcmap-v4-places","website":null,"country":null,"city":null,"explicit_support":"Papa rizz healthy living is listed in BTC Map as a physical place that accepts Bitcoin.","notes":["BTC Map place id: 28403","BTC Map verified_at: 2025-08-17","BTC Map updated_at: 2025-09-18T05:36:30.545Z","BTC Map address: Manyanja Road Nairobi","OSM: https://www.openstreetmap.org/node/13075949530","lat/lon: -1.290859, 36.8910383"]},{"id":"merchant:jennifer-musya:btcmap-place-28404","name":"Jennifer Musya","source":"btcmap-v4-places","website":null,"country":null,"city":null,"explicit_support":"Jennifer Musya is listed in BTC Map as a physical place that accepts Bitcoin.","notes":["BTC Map place id: 28404","BTC Map verified_at: 2025-08-17","BTC Map updated_at: 2025-09-18T05:36:30.545Z","BTC Map address: Manyanja Road Nairobi","OSM: https://www.openstreetmap.org/node/13075958279","lat/lon: -1.2906924, 36.8909767"]},{"id":"merchant:chips-point:btcmap-place-28406","name":"Chips point","source":"btcmap-v4-places","website":null,"country":null,"city":null,"explicit_support":"Chips point is listed in BTC Map as a physical place that accepts Bitcoin.","notes":["BTC Map place id: 28406","BTC Map verified_at: 2025-08-17","BTC Map updated_at: 2025-09-18T05:36:30.545Z","BTC Map address: Manyanja Road Nairobi","OSM: https://www.openstreetmap.org/node/13076006785","lat/lon: -1.2909333, 36.891067"]},{"id":"merchant:biertempel-pub:btcmap-place-24881","name":"Biertempel Pub","source":"btcmap-v4-places","website":null,"country":null,"city":null,"explicit_support":"Biertempel Pub is listed in BTC Map as a physical place that accepts Bitcoin.","notes":["BTC Map place id: 24881","BTC Map verified_at: 2025-08-17","BTC Map updated_at: 2025-09-18T05:36:30.546Z","BTC Map address: 7 Via Molise Fornelli 86070","OSM: https://www.openstreetmap.org/node/4598346052","lat/lon: 41.6066197, 14.1404734"]},{"id":"merchant:unity-industrial-chemical-soap:btcmap-place-28407","name":"Unity Industrial Chemical Soap","source":"btcmap-v4-places","website":null,"country":null,"city":null,"explicit_support":"Unity Industrial Chemical Soap is listed in BTC Map as a physical place that accepts Bitcoin.","notes":["BTC Map place id: 28407","BTC Map verified_at: 2025-08-17","BTC Map updated_at: 2025-09-18T05:36:30.546Z","BTC Map address: Jogoo Road Nairobi","OSM: https://www.openstreetmap.org/node/13076011549","lat/lon: -1.294077, 36.8881469"]},{"id":"merchant:boerderijwinkel-fluitenberg:btcmap-place-28413","name":"Boerderijwinkel Fluitenberg","source":"btcmap-v4-places","website":null,"country":null,"city":null,"explicit_support":"Boerderijwinkel Fluitenberg is listed in BTC Map as a physical place that accepts Bitcoin.","notes":["BTC Map place id: 28413","BTC Map verified_at: 2025-08-17","BTC Map updated_at: 2025-09-18T05:36:30.547Z","BTC Map address: 3 Domeinweg Fluitenberg 7931TJ","OSM: https://www.openstreetmap.org/node/13076635470","lat/lon: 52.7364612, 6.4289284"]},{"id":"merchant:hope-mobile-hofer:btcmap-place-26030","name":"Hope Mobile Hofer","source":"btcmap-v4-places","website":"https://www.hopemobilehofer.com/","country":null,"city":null,"explicit_support":"Hope Mobile Hofer is listed in BTC Map as a physical place that accepts Bitcoin.","notes":["BTC Map place id: 26030","BTC Map verified_at: 2025-08-18","BTC Map updated_at: 2025-09-18T05:36:30.548Z","BTC Map address: 5 Sportplatzstrasse Susten 3952","OSM: https://www.openstreetmap.org/node/12845181627","lat/lon: 46.3085399, 7.6416497"]},{"id":"merchant:ojos-del-mar:btcmap-place-28368","name":"Ojos Del Mar","source":"btcmap-v4-places","website":"https://www.ojosdelmar.com/","country":null,"city":null,"explicit_support":"Ojos Del Mar is listed in BTC Map as a physical place that accepts Bitcoin.","notes":["BTC Map place id: 28368","BTC Map verified_at: 2025-08-13","BTC Map updated_at: 2025-09-18T05:36:30.548Z","BTC Map address: 9 Garden Plaza Tamarindo 50309","OSM: https://www.openstreetmap.org/node/13064693542","lat/lon: 10.3085141, -85.8308256"]},{"id":"merchant:layer-house:btcmap-place-28380","name":"Layer House","source":"btcmap-v4-places","website":"https://layerhouse.blogspot.com/","country":null,"city":null,"explicit_support":"Layer House is listed in BTC Map as a physical place that accepts Bitcoin.","notes":["BTC Map place id: 28380","BTC Map verified_at: 2025-08-18","BTC Map updated_at: 2025-09-18T05:36:30.548Z","BTC Map address: 9/2-7 ซอยอินทามระ 33 10400","OSM: https://www.openstreetmap.org/node/13071813034","lat/lon: 13.7898584, 100.5622319"]},{"id":"merchant:ziil-immo-und-technik:btcmap-place-24785","name":"Ziil Immo und Technik","source":"btcmap-v4-places","website":"https://ziilimmo.ch/","country":null,"city":null,"explicit_support":"Ziil Immo und Technik is listed in BTC Map as a physical place that accepts Bitcoin.","notes":["BTC Map place id: 24785","BTC Map verified_at: 2025-08-18","BTC Map updated_at: 2025-09-18T05:36:30.549Z","BTC Map address: 3 Löwenschanz Kreuzlingen 8280","OSM: https://www.openstreetmap.org/node/12728726057","lat/lon: 47.6481174, 9.173831"]},{"id":"merchant:anarchy-chocolate:btcmap-place-28359","name":"Anarchy Chocolate","source":"btcmap-v4-places","website":"https://anarchychocolate.com/","country":null,"city":null,"explicit_support":"Anarchy Chocolate is listed in BTC Map as a physical place that accepts Bitcoin.","notes":["BTC Map place id: 28359","BTC Map verified_at: 2025-08-18","BTC Map updated_at: 2025-09-18T05:36:30.549Z","BTC Map address: 52/1 23130","OSM: https://www.openstreetmap.org/node/13068215905","lat/lon: 12.3739779, 102.4720179"]},{"id":"merchant:nonie-s:btcmap-place-28419","name":"Nonie’s","source":"btcmap-v4-places","website":"https://www.nonies.com.ph","country":null,"city":null,"explicit_support":"Nonie’s is listed in BTC Map as a physical place that accepts Bitcoin.","notes":["BTC Map place id: 28419","BTC Map verified_at: 2025-08-18","BTC Map updated_at: 2025-09-18T05:36:30.549Z","BTC Map address: Calle Remedios Malay 5608","OSM: https://www.openstreetmap.org/node/4907291521","lat/lon: 11.9568903, 121.9302768"]},{"id":"merchant:litte-taj:btcmap-place-28420","name":"Litte Taj","source":"btcmap-v4-places","website":null,"country":null,"city":null,"explicit_support":"Litte Taj is listed in BTC Map as a physical place that accepts Bitcoin.","notes":["BTC Map place id: 28420","BTC Map verified_at: 2025-08-18","BTC Map updated_at: 2025-09-18T05:36:30.55Z","OSM: https://www.openstreetmap.org/node/11006728477","lat/lon: 11.961588, 121.9248095"]},{"id":"merchant:muchos:btcmap-place-28421","name":"Muchos","source":"btcmap-v4-places","website":"https://muchosboracay.com/","country":null,"city":null,"explicit_support":"Muchos is listed in BTC Map as a physical place that accepts Bitcoin.","notes":["BTC Map place id: 28421","BTC Map verified_at: 2025-08-18","BTC Map updated_at: 2025-09-18T05:36:30.55Z","OSM: https://www.openstreetmap.org/node/13078443917","lat/lon: 11.9637323, 121.9231009"]},{"id":"merchant:island-izakaya:btcmap-place-28422","name":"Island Izakaya","source":"btcmap-v4-places","website":null,"country":null,"city":null,"explicit_support":"Island Izakaya is listed in BTC Map as a physical place that accepts Bitcoin.","notes":["BTC Map place id: 28422","BTC Map verified_at: 2025-08-18","BTC Map updated_at: 2025-09-18T05:36:30.55Z","OSM: https://www.openstreetmap.org/node/12428340502","lat/lon: 11.9550829, 121.9316102"]},{"id":"merchant:kai-kai-bora-bora:btcmap-place-23772","name":"Kai Kai Bora Bora","source":"btcmap-v4-places","website":null,"country":null,"city":null,"explicit_support":"Kai Kai Bora Bora is listed in BTC Map as a physical place that accepts Bitcoin.","notes":["BTC Map place id: 23772","BTC Map place entry has no verified_at value in selected fields.","BTC Map updated_at: 2025-09-18T05:36:30.551Z","BTC Map address: Pago Vaitape 98730","OSM: https://www.openstreetmap.org/node/12577062125","lat/lon: -16.5149706, -151.7366817"]},{"id":"merchant:pousada-victoria:btcmap-place-24962","name":"Pousada Victória","source":"btcmap-v4-places","website":"https://www.airbnb.com.br/rooms/1291313501205605084?viralityEntryPoint=1&s=76","country":null,"city":null,"explicit_support":"Pousada Victória is listed in BTC Map as a physical place that accepts Bitcoin.","notes":["BTC Map place id: 24962","BTC Map verified_at: 2025-08-18","BTC Map updated_at: 2025-09-18T05:36:30.551Z","BTC Map address: 365 Rua Chico Mota Fortaleza","OSM: https://www.openstreetmap.org/node/12729683999","lat/lon: -3.7863805, -38.5219406"]},{"id":"merchant:loja-armeiro:btcmap-place-28424","name":"Loja Armeiro","source":"btcmap-v4-places","website":null,"country":null,"city":null,"explicit_support":"Loja Armeiro is listed in BTC Map as a physical place that accepts Bitcoin.","notes":["BTC Map place id: 28424","BTC Map verified_at: 2025-08-18","BTC Map updated_at: 2025-09-18T05:36:30.551Z","BTC Map address: 46 Rua Duque de Caxias Panambi 98280000","OSM: https://www.openstreetmap.org/node/13078522081","lat/lon: -28.2950408, -53.5030057"]},{"id":"merchant:beyond-softserve:btcmap-place-24198","name":"Beyond Softserve","source":"btcmap-v4-places","website":null,"country":null,"city":null,"explicit_support":"Beyond Softserve is listed in BTC Map as a physical place that accepts Bitcoin.","notes":["BTC Map place id: 24198","BTC Map verified_at: 2025-08-19","BTC Map updated_at: 2025-09-18T05:36:30.552Z","BTC Map address: ถนนป๋วย อิ้งภากรณ์ 12120","OSM: https://www.openstreetmap.org/node/12624732106","lat/lon: 14.0696113, 100.6044915"]},{"id":"merchant:je-lek-fruit-shop:btcmap-place-27248","name":"Je Lek Fruit Shop","source":"btcmap-v4-places","website":null,"country":null,"city":null,"explicit_support":"Je Lek Fruit Shop is listed in BTC Map as a physical place that accepts Bitcoin.","notes":["BTC Map place id: 27248","BTC Map verified_at: 2025-08-19","BTC Map updated_at: 2025-09-18T05:36:30.552Z","BTC Map address: 288/23 Donnok Rd 84000","OSM: https://www.openstreetmap.org/node/13008200881","lat/lon: 9.1337749, 99.345858"]},{"id":"merchant:tonnam-homestay:btcmap-place-28408","name":"Tonnam Homestay","source":"btcmap-v4-places","website":null,"country":null,"city":null,"explicit_support":"Tonnam Homestay is listed in BTC Map as a physical place that accepts Bitcoin.","notes":["BTC Map place id: 28408","BTC Map verified_at: 2025-08-19","BTC Map updated_at: 2025-09-18T05:36:30.553Z","BTC Map address: 216 Patan Road 50300","OSM: https://www.openstreetmap.org/node/13076053766","lat/lon: 18.8326066, 98.9921106"]},{"id":"merchant:lashes-by-lupe:btcmap-place-28415","name":"Lashes By Lupe","source":"btcmap-v4-places","website":"https://lblartistry.com/","country":null,"city":null,"explicit_support":"Lashes By Lupe is listed in BTC Map as a physical place that accepts Bitcoin.","notes":["BTC Map place id: 28415","BTC Map verified_at: 2025-08-17","BTC Map updated_at: 2025-09-18T05:36:30.553Z","BTC Map address: 1667 Renfrew Street Vancouver V5K 4E1","OSM: https://www.openstreetmap.org/node/11378440236","payment_provider: coinos","lat/lon: 49.269899, -123.044463"]},{"id":"merchant:peixing-clinic:btcmap-place-28427","name":"Peixing clinic","source":"btcmap-v4-places","website":null,"country":null,"city":null,"explicit_support":"Peixing clinic is listed in BTC Map as a physical place that accepts Bitcoin.","notes":["BTC Map place id: 28427","BTC Map verified_at: 2025-08-19","BTC Map updated_at: 2025-09-18T05:36:30.553Z","BTC Map address: 30/1 ถนนรังสิต-นครนายก 59 12130","OSM: https://www.openstreetmap.org/node/13081282309","lat/lon: 13.9972327, 100.6703365"]},{"id":"merchant:blue-peter:btcmap-place-23324","name":"Blue Peter","source":"btcmap-v4-places","website":"https://bluepeter.fi/","country":null,"city":null,"explicit_support":"Blue Peter is listed in BTC Map as a physical place that accepts Bitcoin.","notes":["BTC Map place id: 23324","BTC Map verified_at: 2025-08-19","BTC Map updated_at: 2025-09-18T05:36:30.554Z","BTC Map address: 1 Vattuniemen puistotie Helsinki 00210","OSM: https://www.openstreetmap.org/way/93983220","lat/lon: 60.15164195, 24.89151235"]},{"id":"merchant:marktstand:btcmap-place-24945","name":"Marktstand","source":"btcmap-v4-places","website":null,"country":null,"city":null,"explicit_support":"Marktstand is listed in BTC Map as a physical place that accepts Bitcoin.","notes":["BTC Map place id: 24945","BTC Map verified_at: 2025-08-19","BTC Map updated_at: 2025-09-18T05:36:30.554Z","BTC Map address: Uetliberg 8143","OSM: https://www.openstreetmap.org/node/10083261940","lat/lon: 47.3495906, 8.4913704"]},{"id":"merchant:horm-cha-ramkhamhaeng-52:btcmap-place-28428","name":"Horm Cha @ Ramkhamhaeng 52","source":"btcmap-v4-places","website":null,"country":null,"city":null,"explicit_support":"Horm Cha @ Ramkhamhaeng 52 is listed in BTC Map as a physical place that accepts Bitcoin.","notes":["BTC Map place id: 28428","BTC Map verified_at: 2025-08-19","BTC Map updated_at: 2025-09-18T05:36:30.554Z","BTC Map address: 110 74/5 ซอยรามคำแหง 52/2 10240","OSM: https://www.openstreetmap.org/node/13081317028","lat/lon: 13.7568425, 100.6434134"]},{"id":"merchant:moes-manufaktur:btcmap-place-28430","name":"Moes Manufaktur","source":"btcmap-v4-places","website":"https://moesmanufaktur.de/","country":null,"city":null,"explicit_support":"Moes Manufaktur is listed in BTC Map as a physical place that accepts Bitcoin.","notes":["BTC Map place id: 28430","BTC Map verified_at: 2025-08-19","BTC Map updated_at: 2025-09-18T05:36:30.554Z","BTC Map address: 6a Rosengasse Treuchtlingen 91757","OSM: https://www.openstreetmap.org/node/13082203576","lat/lon: 48.9421839, 10.9300852"]},{"id":"merchant:barbearia-velho-chico:btcmap-place-27617","name":"Barbearia Velho Chico","source":"btcmap-v4-places","website":null,"country":null,"city":null,"explicit_support":"Barbearia Velho Chico is listed in BTC Map as a physical place that accepts Bitcoin.","notes":["BTC Map place id: 27617","BTC Map verified_at: 2025-08-19","BTC Map updated_at: 2025-09-18T05:36:30.555Z","BTC Map address: 05 Setor L Norte EQNL 6 8 Brasilia 72155512","OSM: https://www.openstreetmap.org/node/13032150664","lat/lon: -15.8262312, -48.079055"]},{"id":"merchant:prof-denis-costalunga:btcmap-place-28365","name":"prof. Denis Costalunga","source":"btcmap-v4-places","website":"https://www.deniscostalunga.it/","country":null,"city":null,"explicit_support":"prof. Denis Costalunga is listed in BTC Map as a physical place that accepts Bitcoin.","notes":["BTC Map place id: 28365","BTC Map verified_at: 2025-08-15","BTC Map updated_at: 2025-09-18T05:36:30.555Z","BTC Map address: 5/B Via Aldo Moro Marano Vicentino 36035","OSM: https://www.openstreetmap.org/node/13066488798","lat/lon: 45.6920542, 11.4322133"]},{"id":"merchant:the-expat:btcmap-place-28432","name":"The Expat","source":"btcmap-v4-places","website":"https://www.theexpat.nyc/","country":null,"city":null,"explicit_support":"The Expat is listed in BTC Map as a physical place that accepts Bitcoin.","notes":["BTC Map place id: 28432","BTC Map verified_at: 2025-08-19","BTC Map updated_at: 2025-09-18T05:36:30.555Z","BTC Map address: 64 Tiemann Place New York 10027","OSM: https://www.openstreetmap.org/node/2768451052","lat/lon: 40.8154613, -73.9600115"]},{"id":"merchant:meliponario-trentino:btcmap-place-28433","name":"Meliponário Trentino","source":"btcmap-v4-places","website":null,"country":null,"city":null,"explicit_support":"Meliponário Trentino is listed in BTC Map as a physical place that accepts Bitcoin.","notes":["BTC Map place id: 28433","BTC Map verified_at: 2025-08-19","BTC Map updated_at: 2025-09-18T05:36:30.555Z","BTC Map address: 705 Rua José Pompermayer Piracicaba 13411-580","OSM: https://www.openstreetmap.org/node/13082610252","lat/lon: -22.6175069, -47.7399156"]},{"id":"merchant:snack4track:btcmap-place-26976","name":"snack4track","source":"btcmap-v4-places","website":"https://www.snack4track.com/","country":null,"city":null,"explicit_support":"snack4track is listed in BTC Map as a physical place that accepts Bitcoin.","notes":["BTC Map place id: 26976","BTC Map verified_at: 2025-08-17","BTC Map updated_at: 2025-09-18T05:36:30.556Z","BTC Map address: Kostelecká Prostějov","OSM: https://www.openstreetmap.org/node/12991966235","lat/lon: 49.4931082, 17.0832413"]}]}
