[
  {
    "registry_id": "merchant:purevpn:coingate",
    "geo": {
      "lat": 18.4286,
      "lng": -64.6184
    },
    "notes_append": [
      "Filled PureVPN coordinates from Intershore Chambers address-level records in Road Town, Tortola VG1110, matching the official PureVPN mailing address at Intershore Chambers, P.O. Box 4342."
    ]
  },
  {
    "registry_id": "merchant:hostinger:bitpay",
    "contact_channels": [
      { "type": "support_url", "value": "https://www.hostinger.com/contacts", "label": "Contact page" },
      { "type": "email", "value": "domains@hostinger.com", "label": "Domains contact" },
      { "type": "phone", "value": "+370 68424669", "label": "Registrar phone" }
    ],
    "notes_append": [
      "Added Hostinger registrar contact details from InterNIC and aligned office location with the official Hostinger contacts page."
    ]
  }
]
